{
    "2015-02-22": [
        {
            "retweets": 0,
            "favorites": 0,
            "text": "apple ipad air st generation gb wifi in silver ipadair",
            "link": "https://twitter.com/iPadAirsales/status/569647169281662976"
        },
        {
            "retweets": 1,
            "favorites": 2,
            "text": "jeffreyimbrogno pretty soon youll have your own lexus congrats on the free ipad",
            "link": "https://twitter.com/LarryTheSusLord/status/569646724266004481"
        },
        {
            "retweets": 1,
            "favorites": 1,
            "text": "the sooner you get group dms on an ipad the better its so frustrating",
            "link": "https://twitter.com/IsMiseKaliyah/status/569647665585250304"
        },
        {
            "retweets": 0,
            "favorites": 2,
            "text": "okay so i finally have my station set up with my ballot my ipad and pens and chargers",
            "link": "https://twitter.com/cutecarstairs/status/569647572811259905"
        },
        {
            "retweets": 0,
            "favorites": 4,
            "text": "when you get on your moms ipad and comment on your friends ig posts pictwittercomsgfgwjgz",
            "link": "https://twitter.com/_thesamcook/status/569647552850579456"
        },
        {
            "retweets": 1,
            "favorites": 2,
            "text": "whoreheycorona sagatfrancois makes my ipad extra sexy pictwittercomfottqaub wwwoowww",
            "link": "https://twitter.com/cusswiley/status/569647293168816130"
        },
        {
            "retweets": 0,
            "favorites": 2,
            "text": "if you have tried to text me i havent been ignoring you my phone is dead ive been using my ipad i feel like my phone is blowing up",
            "link": "https://twitter.com/TheDopplerDax/status/569647173677101056"
        },
        {
            "retweets": 0,
            "favorites": 1,
            "text": "appleipadtvcmmake a film with ipad",
            "link": "https://twitter.com/nabe888/status/569646508816990209"
        },
        {
            "retweets": 1,
            "favorites": 1,
            "text": "apples oscar ad shot entirely on an ipad macrumors aapl",
            "link": "https://twitter.com/MacHashNews/status/569646478328639489"
        },
        {
            "retweets": 1,
            "favorites": 1,
            "text": "cant get my twitter on ipad grrrrr wont accept my pw xx",
            "link": "https://twitter.com/Can_2Ton/status/569646438914908161"
        },
        {
            "retweets": 0,
            "favorites": 2,
            "text": "ylolamaried fuck this weeks episode i honestly threw my ipad across the room i felt so many things",
            "link": "https://twitter.com/ercsuperman85/status/569645863179554816"
        },
        {
            "retweets": 2,
            "favorites": 0,
            "text": "watch apples new ipad commercial set to air during oscars incartriver",
            "link": "https://twitter.com/troylsmith/status/569645837015511040"
        },
        {
            "retweets": 0,
            "favorites": 2,
            "text": "today was my first fullon use of microsoftoffice on the ipad and i was quite impressed microsoft apple office word",
            "link": "https://twitter.com/Muswell_Ben/status/569645519083081728"
        },
        {
            "retweets": 2,
            "favorites": 1,
            "text": "onlydesisknow ive been hit with an ipad",
            "link": "https://twitter.com/funny_brown_kid/status/569645420139454466"
        },
        {
            "retweets": 1,
            "favorites": 1,
            "text": "apples oscars ad shot entirely on ipad air features voiceover by martin scorsese just in time for apple",
            "link": "https://twitter.com/HMBangash/status/569644720797777920"
        },
        {
            "retweets": 0,
            "favorites": 3,
            "text": "let me just hold my ipad over this foot bridge pictwittercomouovbren",
            "link": "https://twitter.com/lance_rosko/status/569644695669874688"
        },
        {
            "retweets": 0,
            "favorites": 2,
            "text": "when two arch rivals put their minds together the results can be quite good using microsoft word on the ipad pictwittercomyrvqjwfv",
            "link": "https://twitter.com/Muswell_Ben/status/569644555127164928"
        },
        {
            "retweets": 2,
            "favorites": 3,
            "text": "it is easier to upload a video from my ipad to youtube then download it from youtube than it is to copy it with a usb cable",
            "link": "https://twitter.com/LewieP/status/569643607252197376"
        },
        {
            "retweets": 2,
            "favorites": 2,
            "text": "watch oscars live online on pc android iphone and ipad oscarsliveonlineonpcandroidiphoneandipad",
            "link": "https://twitter.com/Ordet_er_frit_/status/569642858057052160"
        },
        {
            "retweets": 2,
            "favorites": 14,
            "text": "carolyn switched it up and sent the email from her droid instead of her ipad but i can dig it",
            "link": "https://twitter.com/lindsrussell10/status/569642606256394241"
        },
        {
            "retweets": 0,
            "favorites": 0,
            "text": "xxx movie german amateur bitch gangbanged xxx anal milf ipad usa",
            "link": "https://twitter.com/babeCharlotte1/status/569642578280378368"
        },
        {
            "retweets": 0,
            "favorites": 5,
            "text": "qvc selling ipad mini caller i have no idea what this stuff is about but im buying one for my grandchild",
            "link": "https://twitter.com/neilcybart/status/569642282464518144"
        },
        {
            "retweets": 8,
            "favorites": 90,
            "text": "the next followers of lovephrase will receive a gold plated ipad go go go fav when done",
            "link": "https://twitter.com/HeaIthyLongHair/status/569642142844346369"
        },
        {
            "retweets": 9,
            "favorites": 8,
            "text": "sixers using an ipad on the bench to look at tape in real time pretty cool pictwittercomirqeyvgf",
            "link": "https://twitter.com/MaxOnTwitter/status/569641564043120641"
        },
        {
            "retweets": 2,
            "favorites": 2,
            "text": "dont forget to follow us so we can message you if you win the ipad air boomoscars",
            "link": "https://twitter.com/boomcornwall/status/569640632119103488"
        },
        {
            "retweets": 29,
            "favorites": 53,
            "text": "apples oscar ad shot entirely on an ipad oscaradshotentirelyonanipad by arnoldkim",
            "link": "https://twitter.com/MacRumors/status/569635812108673024"
        },
        {
            "retweets": 0,
            "favorites": 0,
            "text": "free ios wallpaper ipad via gadget and tech",
            "link": "https://twitter.com/fajardemos/status/569627179459293184"
        },
        {
            "retweets": 0,
            "favorites": 0,
            "text": "apple ipad air st gengb wifi in silver bundle w bt keyboard ipadair",
            "link": "https://twitter.com/iPadAirsales/status/569624118473203712"
        },
        {
            "retweets": 0,
            "favorites": 0,
            "text": "restaurant tropiko war groartig ist jetzt aber sogar noch besser ipad ipadgames gameinsight",
            "link": "https://twitter.com/xareltoman73/status/569622487279005696"
        },
        {
            "retweets": 0,
            "favorites": 0,
            "text": "ich habe stewardess violetta in meiner airport city getroffen ipad ipadgames gameinsight",
            "link": "https://twitter.com/1973mmkal/status/569620405788532736"
        },
        {
            "retweets": 0,
            "favorites": 0,
            "text": "ich habe mr stern ingenieur in meiner airport city getroffen ipad ipadgames gameinsight",
            "link": "https://twitter.com/1973mmkal/status/569613052590600192"
        },
        {
            "retweets": 0,
            "favorites": 0,
            "text": "ich habe flugkapitn kim in meiner airport city getroffen ipad ipadgames gameinsight",
            "link": "https://twitter.com/1973mmkal/status/569612135858376704"
        },
        {
            "retweets": 0,
            "favorites": 0,
            "text": "neues flugzeug in meiner airport city turboprop ipad ipadgames gameinsight",
            "link": "https://twitter.com/1973mmkal/status/569612135778656257"
        },
        {
            "retweets": 0,
            "favorites": 0,
            "text": "ipad air mini iphones c s ipod nano touch macbookpro air im",
            "link": "https://twitter.com/ProdukSidoarjo/status/569610658611732480"
        },
        {
            "retweets": 0,
            "favorites": 0,
            "text": "apple ipad air st generation gb wifi in silver",
            "link": "https://twitter.com/kamzou08/status/569610560070750208"
        },
        {
            "retweets": 0,
            "favorites": 0,
            "text": "emperorleather crafterei ipad air hlletasche amarettini pictwittercomzmermtqay",
            "link": "https://twitter.com/EmperorLeather/status/569609284675346433"
        },
        {
            "retweets": 0,
            "favorites": 0,
            "text": "das leben in mayors stadt wird immer besser mycountry ipad ipadgames gameinsight",
            "link": "https://twitter.com/PaddyNady/status/569608495949066241"
        },
        {
            "retweets": 0,
            "favorites": 1,
            "text": "ich habe ein youtubevideo positiv bewertet lvfwaqxa ipad make a film with ipad",
            "link": "https://twitter.com/techniklike/status/569608327832801281"
        },
        {
            "retweets": 0,
            "favorites": 0,
            "text": "neues angebot apple ipad air gb wifi cellular silber",
            "link": "https://twitter.com/Shopschnueffler/status/569606175114661888"
        },
        {
            "retweets": 0,
            "favorites": 0,
            "text": "ich habe techniker sascha in meiner airport city getroffen ipad ipadgames gameinsight",
            "link": "https://twitter.com/Mick_berlin/status/569602423112790017"
        },
        {
            "retweets": 1,
            "favorites": 0,
            "text": "ein ipad pro prototyp auf ebay wohl eher nicht ipadproprototype",
            "link": "https://twitter.com/apfelpage_de/status/569599530196467712"
        },
        {
            "retweets": 0,
            "favorites": 1,
            "text": "ich habe ein youtubevideo positiv bewertet lvfwaqxa ipad make a film with ipad",
            "link": "https://twitter.com/iReviewGER/status/569595838860812288"
        },
        {
            "retweets": 0,
            "favorites": 0,
            "text": "ich habe stewardess jane in meiner airport city getroffen ipad ipadgames gameinsight",
            "link": "https://twitter.com/1973mmkal/status/569595736297488384"
        },
        {
            "retweets": 0,
            "favorites": 0,
            "text": "ich habe ein youtubevideo positiv bewertet lvfwaqxa ipad make a film with ipad",
            "link": "https://twitter.com/iPhoneCrackx/status/569594483089797120"
        },
        {
            "retweets": 0,
            "favorites": 0,
            "text": "ich habe reisekauffrau salma in meiner airport city getroffen ipad ipadgames gameinsight",
            "link": "https://twitter.com/1973mmkal/status/569593114056380418"
        },
        {
            "retweets": 98,
            "favorites": 46,
            "text": "apples oscar ad pitches ipad as filmmaking tool pictwittercombfgzvsw",
            "link": "https://twitter.com/mashable/status/569586839968997378"
        },
        {
            "retweets": 0,
            "favorites": 0,
            "text": "ich habe stewardess violetta in meiner airport city getroffen ipad ipadgames gameinsight",
            "link": "https://twitter.com/1973mmkal/status/569585380430901249"
        },
        {
            "retweets": 0,
            "favorites": 0,
            "text": "ich habe mr wulf sammler in meiner airport city getroffen ipad ipadgames gameinsight",
            "link": "https://twitter.com/eberlmeister/status/569584642820595712"
        },
        {
            "retweets": 0,
            "favorites": 0,
            "text": "ich habe fluglotse sven in meiner airport city getroffen ipad ipadgames gameinsight",
            "link": "https://twitter.com/1973mmkal/status/569583506919178240"
        },
        {
            "retweets": 0,
            "favorites": 0,
            "text": "apple ipad air st generation gb wifi in silver ipadair",
            "link": "https://twitter.com/iPadAirsales/status/569583181021773824"
        },
        {
            "retweets": 0,
            "favorites": 0,
            "text": "ich habe techniker sascha in meiner airport city getroffen ipad ipadgames gameinsight",
            "link": "https://twitter.com/kreibich2/status/569580743321640960"
        },
        {
            "retweets": 0,
            "favorites": 0,
            "text": "brad erkkila games ipad owens odyssey ver owens odyssey is the pictwittercomalsqpqbk",
            "link": "https://twitter.com/gima2327/status/569580681359007745"
        },
        {
            "retweets": 0,
            "favorites": 0,
            "text": "webinar workflow mit dem ipad andreas hofmann h h info pictwittercomvrwxxudi",
            "link": "https://twitter.com/wagjuer/status/569579001955684352"
        },
        {
            "retweets": 0,
            "favorites": 0,
            "text": "ich fertigte in paradise island einen smaragd gameinsight ipadgames ipad",
            "link": "https://twitter.com/pauherm/status/569578725051924482"
        },
        {
            "retweets": 83,
            "favorites": 114,
            "text": "apple shot its new ad on the ipad air pictwittercomrmcqolbpq",
            "link": "https://twitter.com/verge/status/569578417861083136"
        },
        {
            "retweets": 0,
            "favorites": 0,
            "text": "apple ipad air st generation gb wifi in silver",
            "link": "https://twitter.com/kamzou08/status/569575925634834433"
        },
        {
            "retweets": 0,
            "favorites": 0,
            "text": "ich habe ein youtubevideo von jesseridgway positiv bewertet psycho girlfriend breaks ipad",
            "link": "https://twitter.com/PvPSgttolga/status/569568218764976128"
        },
        {
            "retweets": 0,
            "favorites": 0,
            "text": "ich habe jetzt rammbock und was ist mit dir ipad ipadgames gameinsight",
            "link": "https://twitter.com/harke_denise/status/569568126297374720"
        },
        {
            "retweets": 0,
            "favorites": 0,
            "text": "emperorleather crafterei ipad air hlletasche amarettini pictwittercompxzfdhicl",
            "link": "https://twitter.com/EmperorLeather/status/569564503807008768"
        },
        {
            "retweets": 0,
            "favorites": 0,
            "text": "machen sie mit bei paradise island hd fr ipad ipad ipadgames gameinsightpictwittercomqffhzbh",
            "link": "https://twitter.com/GolaClaussen/status/569557474887512064"
        },
        {
            "retweets": 0,
            "favorites": 0,
            "text": "machen sie mit bei paradise island hd fr ipad ipad ipadgames gameinsightpictwittercomewdjrg",
            "link": "https://twitter.com/Kalidera/status/569556821104594945"
        },
        {
            "retweets": 63,
            "favorites": 265,
            "text": "elastic heart parody behind the scenes im giving away an ipad watch to find out how to win",
            "link": "https://twitter.com/BartBaker/status/569556110538964993"
        },
        {
            "retweets": 0,
            "favorites": 0,
            "text": "dog soundboard dogs chihuahua german shepherd labrador rottweiler ipad iphone app",
            "link": "https://twitter.com/iPhoneAppDeal/status/569551209566089216"
        },
        {
            "retweets": 0,
            "favorites": 0,
            "text": "ihdi ipad air leak jailbreak iphone rumors ios untethered wildstar ps qua youtube",
            "link": "https://twitter.com/phamvandong110/status/569548173204697088"
        },
        {
            "retweets": 0,
            "favorites": 0,
            "text": "amazon blitzangebote philips hue tb nassystem iphone ipad zubehr macerkopf apple news aus cupert",
            "link": "https://twitter.com/DJV_Berlin/status/569543131907153923"
        },
        {
            "retweets": 0,
            "favorites": 0,
            "text": "bowlingclub war groartig ist jetzt aber sogar noch besser ipad ipadgames gameinsight",
            "link": "https://twitter.com/WilfriedBehren1/status/569523454275399680"
        },
        {
            "retweets": 0,
            "favorites": 0,
            "text": "ich habe mr stern ingenieur in meiner airport city getroffen ipad ipadgames gameinsight",
            "link": "https://twitter.com/hstoelker120673/status/569521182871060480"
        },
        {
            "retweets": 0,
            "favorites": 0,
            "text": "emperorleather crafterei ipad air hlletasche amarettini pictwittercomulejvvnl",
            "link": "https://twitter.com/EmperorLeather/status/569520751264575488"
        },
        {
            "retweets": 0,
            "favorites": 0,
            "text": "ich habe ein youtubevideo positiv bewertet the amazing ipad magician",
            "link": "https://twitter.com/Kuchen89/status/569515388926611456"
        },
        {
            "retweets": 0,
            "favorites": 0,
            "text": "ich habe ein neues gebiet in the tribez entdeckt ipad ipadgames gameinsight",
            "link": "https://twitter.com/schapimaus/status/569506985831505920"
        },
        {
            "retweets": 0,
            "favorites": 0,
            "text": "apple ipad air st generation gb wifi in silver ipadair",
            "link": "https://twitter.com/iPadAirsales/status/569506417939492864"
        },
        {
            "retweets": 0,
            "favorites": 0,
            "text": "hf beam antenna calculator iphone ipod app hamradio ipad",
            "link": "https://twitter.com/iPhoneAppDeal/status/569502573452922882"
        },
        {
            "retweets": 0,
            "favorites": 0,
            "text": "videosoft ipad manager fr epub ipadmanagerfurepub",
            "link": "https://twitter.com/andreeabpanait/status/569498811929722880"
        },
        {
            "retweets": 0,
            "favorites": 0,
            "text": "langelier saturation index calculator lsi iphone water ipad app",
            "link": "https://twitter.com/iPhoneAppDeal/status/569496741885538304"
        },
        {
            "retweets": 0,
            "favorites": 0,
            "text": "ich starte ein raumschiff in meiner airport city ipad ipadgames gameinsight",
            "link": "https://twitter.com/eberlmeister/status/569492796115189760"
        },
        {
            "retweets": 0,
            "favorites": 0,
            "text": "ios frozen synapse free was ipad iphone iosfrozensynapsefreewasipadiphoneaspx",
            "link": "https://twitter.com/SlickdealsCoNz/status/569491235708121089"
        },
        {
            "retweets": 0,
            "favorites": 0,
            "text": "heute versandkostenfrei bestellen mit code freedelivery beim checkout shopping free notizbuch ipad apple sketchnotes promo sunday",
            "link": "https://twitter.com/paperscreen/status/569487138615640064"
        },
        {
            "retweets": 0,
            "favorites": 0,
            "text": "emperorleather crafterei ipad air hlletasche amarettini pictwittercomlyjimmjh",
            "link": "https://twitter.com/EmperorLeather/status/569472237780267008"
        },
        {
            "retweets": 0,
            "favorites": 0,
            "text": "ipad air mini iphones c s ipod nano touch macbookpro air im",
            "link": "https://twitter.com/ProdukSidoarjo/status/569461631144452096"
        },
        {
            "retweets": 0,
            "favorites": 0,
            "text": "ich habe techniker sascha in meiner airport city getroffen ipad ipadgames gameinsight",
            "link": "https://twitter.com/Bundy1002/status/569456615872700416"
        },
        {
            "retweets": 2,
            "favorites": 2,
            "text": "oscars live streamen auf ipad iphone tablet pc xbox usw mit prosieben ab uhrpictwittercomlchhpyq",
            "link": "https://twitter.com/zattoo/status/569453166573559808"
        },
        {
            "retweets": 0,
            "favorites": 0,
            "text": "ipad parthenogenesisway up hypertrophy ipad tent qurenpfp",
            "link": "https://twitter.com/CarterWyatt1/status/569452154672394241"
        },
        {
            "retweets": 0,
            "favorites": 0,
            "text": "machen sie mit bei paradise island hd fr ipad ipad ipadgames gameinsightpictwittercombhvfphtcgi",
            "link": "https://twitter.com/ttgee_sabri/status/569442212607631360"
        },
        {
            "retweets": 0,
            "favorites": 0,
            "text": "machen sie mit bei paradise island hd fr ipad ipad ipadgames gameinsightpictwittercomwvprtreiyo",
            "link": "https://twitter.com/ttgee_sabri/status/569441998354190336"
        },
        {
            "retweets": 0,
            "favorites": 0,
            "text": "machen sie mit bei paradise island hd fr ipad ipad ipadgames gameinsightpictwittercompyfnlomrcs",
            "link": "https://twitter.com/ttgee_sabri/status/569439582489608192"
        },
        {
            "retweets": 0,
            "favorites": 0,
            "text": "ich habe eine aufgabe in mystery manor abgeschlossen steampunk ipad ipadgames gameinsight",
            "link": "https://twitter.com/Cindy37Hfer/status/569431723450052609"
        },
        {
            "retweets": 0,
            "favorites": 0,
            "text": "emperorleather crafterei ipad air hlletasche amarettini pictwittercombjlyfri",
            "link": "https://twitter.com/EmperorLeather/status/569428248360296449"
        },
        {
            "retweets": 0,
            "favorites": 1,
            "text": "xxx movie german amateur bitch gangbanged xxx anal milf ipad usa",
            "link": "https://twitter.com/sex_sexslave/status/569426462362738690"
        },
        {
            "retweets": 0,
            "favorites": 0,
            "text": "das spiralbuch sketchbook passend zum ipad air nur bei uns airsketchbookxvariant ipadair ipad sketchbook notes recycling shop",
            "link": "https://twitter.com/paperscreen/status/569418421261221888"
        },
        {
            "retweets": 0,
            "favorites": 0,
            "text": "google inbox fr ipad und android tablets",
            "link": "https://twitter.com/LANGE_PFLANZ/status/569416302563106817"
        },
        {
            "retweets": 0,
            "favorites": 0,
            "text": "ich fertigte in paradise island einen smaragd gameinsight ipadgames ipad",
            "link": "https://twitter.com/silvia_lindner/status/569410063888228352"
        },
        {
            "retweets": 0,
            "favorites": 0,
            "text": "iphone ipad appstore preissenkung infinite warrior statt",
            "link": "https://twitter.com/AppTicker/status/569408664915865600"
        },
        {
            "retweets": 0,
            "favorites": 0,
            "text": "echt leder tasche fr apple ipad air real leather bag for apple ipad air via easysocialshop",
            "link": "https://twitter.com/Kluge_TascHe/status/569407050347905024"
        },
        {
            "retweets": 0,
            "favorites": 0,
            "text": "apple ipad air st generation gb wifi in silver",
            "link": "https://twitter.com/kamzou08/status/569404715823435777"
        },
        {
            "retweets": 0,
            "favorites": 0,
            "text": "ich habe professor klandau in meiner airport city getroffen ipad ipadgames gameinsight",
            "link": "https://twitter.com/hstoelker120673/status/569404345516724224"
        },
        {
            "retweets": 0,
            "favorites": 0,
            "text": "ich habe jetzt rammbock und was ist mit dir ipad ipadgames gameinsight",
            "link": "https://twitter.com/peter_082/status/569400358168080384"
        },
        {
            "retweets": 0,
            "favorites": 1,
            "text": "ich habe ein youtubevideo positiv bewertet video sketch notes on an ipad",
            "link": "https://twitter.com/web2write/status/569396754451460096"
        },
        {
            "retweets": 0,
            "favorites": 1,
            "text": "i entered to win an ipad mini from meandmyhandful freedomevpn privacyisnogame anipadminifromfsecurefreedomecomment",
            "link": "https://twitter.com/tannawings/status/569381946675073025"
        },
        {
            "retweets": 1,
            "favorites": 2,
            "text": "yungnatedogg thelordfuego jaiimmeeeee that ipad tho",
            "link": "https://twitter.com/rickroddd_12/status/569380820261085184"
        },
        {
            "retweets": 0,
            "favorites": 0,
            "text": "emperorleather crafterei ipad air hlletasche amarettini pictwittercomnlonbl",
            "link": "https://twitter.com/EmperorLeather/status/569380586491670528"
        },
        {
            "retweets": 0,
            "favorites": 1,
            "text": "i hope david e berri will put that app design up on pateron also a daw i can use on my ipad and may be android",
            "link": "https://twitter.com/AnimatedSoundz/status/569380461325070336"
        },
        {
            "retweets": 5,
            "favorites": 2,
            "text": "my ipad battery lasts about a week but i have to charge my phone about three times a day",
            "link": "https://twitter.com/emm8nuel/status/569380111062949889"
        },
        {
            "retweets": 20,
            "favorites": 35,
            "text": "the ipad when i was younger",
            "link": "https://twitter.com/ltTrueQuote/status/569379470756286466"
        },
        {
            "retweets": 0,
            "favorites": 0,
            "text": "neues flugzeug in meiner airport city turboprop ipad ipadgames gameinsight",
            "link": "https://twitter.com/mriesler/status/569378709263785984"
        },
        {
            "retweets": 0,
            "favorites": 1,
            "text": "students can scan the qr anchor charts using and ipad all year long for a quick video reminder of",
            "link": "https://twitter.com/Erintegration/status/569377955220213760"
        },
        {
            "retweets": 0,
            "favorites": 1,
            "text": "start playing big business hd for ipad ipadgames gameinsight ipad pictwittercomktxjaajnz",
            "link": "https://twitter.com/ockenburg/status/569377261150998528"
        },
        {
            "retweets": 0,
            "favorites": 0,
            "text": "crafterei ipad air hlletasche amarettini ipadairtasc pictwittercomzjeowdkke",
            "link": "https://twitter.com/EmperorLeather/status/569376596097941504"
        },
        {
            "retweets": 2,
            "favorites": 0,
            "text": "currently listening to a plies mix via vins ipad",
            "link": "https://twitter.com/A_Cool_Squarian/status/569372641360015360"
        },
        {
            "retweets": 0,
            "favorites": 0,
            "text": "apple named our ther new khan ipad app the best app of january get it here",
            "link": "https://twitter.com/Jrenowitzky/status/569372181089669120"
        },
        {
            "retweets": 0,
            "favorites": 3,
            "text": "loool my little brother is messaging me on his ipad and i cant breathe pictwittercomohbxzdipkz",
            "link": "https://twitter.com/cindy_traaan/status/569371784774094848"
        },
        {
            "retweets": 0,
            "favorites": 2,
            "text": "kiera my ipad wont call you try calling me",
            "link": "https://twitter.com/tiredpadawan/status/569371781745614848"
        },
        {
            "retweets": 0,
            "favorites": 1,
            "text": "pls dont give yr babies an ipadphoneetc to occupy them please",
            "link": "https://twitter.com/_amysalem/status/569371323203321856"
        },
        {
            "retweets": 0,
            "favorites": 2,
            "text": "what will it take for cracked to hire an app developer that doesnt make buggy ipad apps every version they release is a mess",
            "link": "https://twitter.com/BenHowe/status/569371127383871488"
        },
        {
            "retweets": 0,
            "favorites": 2,
            "text": "abort mission too many people around me cant play ll in the ipad too big to much attention with me takatakatakaing on the screen",
            "link": "https://twitter.com/HimeROAR/status/569370504097714176"
        },
        {
            "retweets": 0,
            "favorites": 0,
            "text": "xxx movie german amateur bitch gangbanged xxx anal milf ipad usa",
            "link": "https://twitter.com/BeautifulFemal/status/569367700700573697"
        },
        {
            "retweets": 0,
            "favorites": 0,
            "text": "xxx movie german amateur bitch gangbanged xxx anal milf ipad usa",
            "link": "https://twitter.com/OceanOceans19/status/569367656853311488"
        },
        {
            "retweets": 1,
            "favorites": 26,
            "text": "i carefully lay the ipad on my daughters stomach while shes sleeping to buy a few hours sleep for myself in the morning",
            "link": "https://twitter.com/bottlerocket/status/569365629431631872"
        },
        {
            "retweets": 0,
            "favorites": 2,
            "text": "bbq ipad and pool with my girls in this stinking hot weather can life get any better family funpictwittercomkxthccast",
            "link": "https://twitter.com/peterMVFC/status/569365174366240768"
        },
        {
            "retweets": 5,
            "favorites": 2,
            "text": "modern familys upcoming connection lost episode was shot entirely on iphone and ipad air iphone iphone",
            "link": "https://twitter.com/iPhoneHackx/status/569364713479536640"
        },
        {
            "retweets": 1,
            "favorites": 3,
            "text": "thank the lord for my laptop but i just want my ipad to work kylee pictwittercommziqkvqzyf",
            "link": "https://twitter.com/5idiots5sos/status/569364641538662400"
        },
        {
            "retweets": 0,
            "favorites": 2,
            "text": "moms and my niece wanna facetime but they sont know how to use the ipad lol pictwittercomvcnkutnmq",
            "link": "https://twitter.com/YolaTheDon/status/569364467278057473"
        },
        {
            "retweets": 2,
            "favorites": 19,
            "text": "i want a ipad mini or a big new iphone but mostly the ipad mini this is me using the secret",
            "link": "https://twitter.com/_lizharvey/status/569364288663465984"
        },
        {
            "retweets": 0,
            "favorites": 2,
            "text": "watching csi on my ipad and relaxing cincinati topangapandora moonloght redsfangirl lilisamarieb",
            "link": "https://twitter.com/SWalesJones/status/569363459210682368"
        },
        {
            "retweets": 1,
            "favorites": 2,
            "text": "parytaimmx check out my new youtube video leak release please called octave made on an ipad",
            "link": "https://twitter.com/The_real_bobo4/status/569363188052922368"
        },
        {
            "retweets": 0,
            "favorites": 1,
            "text": "i got to see this ipad mini todays special value in las vegas at the consumer electronics show in january",
            "link": "https://twitter.com/JacqueGonzales/status/569362965859856384"
        },
        {
            "retweets": 0,
            "favorites": 4,
            "text": "my ipad wont fucking work correctly and its pissing me off because i read wattpad on there and it wont load the stories and im crying ky",
            "link": "https://twitter.com/5idiots5sos/status/569362260247732224"
        },
        {
            "retweets": 2,
            "favorites": 2,
            "text": "tonygrossi my yr old son can find a score on his ipad we work in tv video driven the days of cronkite reading graphics are over",
            "link": "https://twitter.com/TonyZ19/status/569361529499459584"
        },
        {
            "retweets": 0,
            "favorites": 7,
            "text": "iphoneipadpictwittercommycgmgwom",
            "link": "https://twitter.com/___hrom67/status/569361493793206273"
        },
        {
            "retweets": 0,
            "favorites": 4,
            "text": "i made this on my ipad with sketchclubapp wild electrical vip eventpictwittercombodibxm",
            "link": "https://twitter.com/vipvip_apel/status/569361369511755776"
        },
        {
            "retweets": 3,
            "favorites": 4,
            "text": "your search is over our ipad mini tsv is on easy pays and ships free",
            "link": "https://twitter.com/QVC/status/569361058466553856"
        },
        {
            "retweets": 0,
            "favorites": 0,
            "text": "xxx movie german amateur bitch gangbanged xxx anal milf ipad usa",
            "link": "https://twitter.com/Melanie6ix/status/569359492208574465"
        },
        {
            "retweets": 0,
            "favorites": 2,
            "text": "never put limitations on innovation the ipod ipad and iphone were invented and produced before we even knew that w",
            "link": "https://twitter.com/solarmikev/status/569358662436671488"
        },
        {
            "retweets": 0,
            "favorites": 2,
            "text": "me estan jakeando el ipad xd pictwittercomhznftamlc",
            "link": "https://twitter.com/fatdoggu/status/569357978698174464"
        },
        {
            "retweets": 2,
            "favorites": 0,
            "text": "a simple way to share your weekend joy with friend check out the new bingbing weekend for iphone ipad weekendhdidlsmt",
            "link": "https://twitter.com/BINGBING_CKTAIL/status/569357818907660288"
        },
        {
            "retweets": 1,
            "favorites": 0,
            "text": "tech time by fraser valley distance education happening now at chiefs game text fvdes to for chance to win mini ipad",
            "link": "https://twitter.com/Chiefs_Hockey/status/569357228160864256"
        },
        {
            "retweets": 1,
            "favorites": 5,
            "text": "welp my ipad screen is shattered thanks to the kiddos surprised it took this long to be honest blametodd katvweather",
            "link": "https://twitter.com/chad_gardner/status/569355904878911488"
        },
        {
            "retweets": 0,
            "favorites": 0,
            "text": "marine cft and pft scores calculators usmc military app iphone ipad",
            "link": "https://twitter.com/iPhoneAppDeal/status/569354433382912001"
        },
        {
            "retweets": 0,
            "favorites": 14,
            "text": "what i find on wills ipadif this doesnt make your night idk what will pictwittercomwlpzzyte",
            "link": "https://twitter.com/EllermanAnnie/status/569354309130825728"
        },
        {
            "retweets": 1,
            "favorites": 6,
            "text": "every night i curl up with my ipad and watch game of thrones its almost like having a fantasyobsessed boyfriend almost",
            "link": "https://twitter.com/alexisthenedd/status/569354036991922176"
        },
        {
            "retweets": 3,
            "favorites": 4,
            "text": "anlisis del juego modern combat de gameloftspain para iphone e ipad moderncombat pictwittercomafitsmru",
            "link": "https://twitter.com/Teknofilo/status/569353412183064577"
        },
        {
            "retweets": 19,
            "favorites": 0,
            "text": "ipad publishing guide michael ashley business personal finance free ebook freebook freeebook business",
            "link": "https://twitter.com/janinebucks/status/569352891380719616"
        },
        {
            "retweets": 2,
            "favorites": 0,
            "text": "rt for a dm to luke free bc i cant do group dms on my ipad",
            "link": "https://twitter.com/hckyeon/status/569352619501596673"
        },
        {
            "retweets": 0,
            "favorites": 0,
            "text": "dog soundboard dogs chihuahua german shepherd labrador rottweiler ipad iphone app",
            "link": "https://twitter.com/iPhoneAppDeal/status/569352274004148224"
        },
        {
            "retweets": 0,
            "favorites": 1,
            "text": "look at the guy in the header photo typing away on his new ipad keyboard isnt it the most uncomfortable position usproductkeystogoipad",
            "link": "https://twitter.com/morrick/status/569352074523246593"
        },
        {
            "retweets": 0,
            "favorites": 2,
            "text": "love how my phone charges in mins to but it takes my ipad days to get there",
            "link": "https://twitter.com/PARKer_THE_CAR_/status/569351635635474433"
        },
        {
            "retweets": 0,
            "favorites": 0,
            "text": "xxx movie german amateur bitch gangbanged xxx anal milf ipad usa",
            "link": "https://twitter.com/PerfectBoobs2/status/569351619294461952"
        },
        {
            "retweets": 1,
            "favorites": 1,
            "text": "download videos from youtube get the youtube to mp converter for pc mac ipad app",
            "link": "https://twitter.com/TheAppShortcut/status/569351548502810624"
        },
        {
            "retweets": 0,
            "favorites": 1,
            "text": "on the plus side the ipad case that i ordered on monday just shipped out today happysaturday notcool",
            "link": "https://twitter.com/maylee_misspell/status/569350254077698049"
        },
        {
            "retweets": 0,
            "favorites": 1,
            "text": "found a buy it now offer for with free shipping so now i own an ipad i guess finally gave in",
            "link": "https://twitter.com/chrisrouse/status/569349378735013889"
        },
        {
            "retweets": 0,
            "favorites": 3,
            "text": "just dropped my ipad on my face i may or may not have a black eye for vacation",
            "link": "https://twitter.com/jewelofcana/status/569349059313590272"
        },
        {
            "retweets": 0,
            "favorites": 0,
            "text": "check out what i saved from black cat in garden watercolor ipad mini case ipad mini case",
            "link": "https://twitter.com/Susang6/status/569348860448911360"
        },
        {
            "retweets": 1,
            "favorites": 1,
            "text": "no ipad no iphone no i anything before bed the light from the screen can disturb your sleep dr sara drsaradetox",
            "link": "https://twitter.com/loseittea/status/569348222600261632"
        },
        {
            "retweets": 0,
            "favorites": 0,
            "text": "astropad transform your ipad into a professional graphics tablet",
            "link": "https://twitter.com/the_menace/status/569348192288038913"
        },
        {
            "retweets": 6,
            "favorites": 6,
            "text": "rt bookcreatorapp of our best book creator tips edtech ipaded ipad edu edchat pictwittercomqixscwqn",
            "link": "https://twitter.com/art_cathyhunt/status/569347722202886144"
        },
        {
            "retweets": 1,
            "favorites": 2,
            "text": "celly carlitos punked me for my ipad at least he didnt punk you for the vitamins",
            "link": "https://twitter.com/lilyyysmalls/status/569347470062256128"
        },
        {
            "retweets": 0,
            "favorites": 0,
            "text": "ich habe stewardess jane in meiner airport city getroffen ipad ipadgames gameinsight",
            "link": "https://twitter.com/Michi200675/status/569346272194371586"
        },
        {
            "retweets": 0,
            "favorites": 1,
            "text": "the offset is that i need to listen to the ipad audio through my tv which has a ms audio delay fixed in rhythm games with timing offset",
            "link": "https://twitter.com/rebukato/status/569346120016646144"
        },
        {
            "retweets": 9,
            "favorites": 6,
            "text": "of the best free education apps for ipad teded edmodo duolingopictwittercomeesmcril",
            "link": "https://twitter.com/TeachersApps/status/569345895013208064"
        },
        {
            "retweets": 0,
            "favorites": 2,
            "text": "mom oh can u heat up the food ill be back in a sec just have to go to the bathroom hears her watching revenge on her ipad in her room",
            "link": "https://twitter.com/noooeeellle/status/569345703639588865"
        },
        {
            "retweets": 0,
            "favorites": 3,
            "text": "movieboxapp hello im a huge fan of movie box but recently i updated movie box on my brothers ipad mini but it keeps saying update error",
            "link": "https://twitter.com/Altius1097/status/569345577047224320"
        },
        {
            "retweets": 1,
            "favorites": 2,
            "text": "ive set my goal to get at least people their ipad bonus with nerium by march st who wants in",
            "link": "https://twitter.com/erin4nerium/status/569345468356026369"
        },
        {
            "retweets": 2,
            "favorites": 1,
            "text": "eileenccampos lyndaflood how many kids do u think will act out knowing will be given a computer an ipad particularly in high school",
            "link": "https://twitter.com/daycogs/status/569345257856479232"
        },
        {
            "retweets": 0,
            "favorites": 1,
            "text": "amazing design rt verge altos adventure is a great ipad snowboarding game pictwittercomznpsbelbc",
            "link": "https://twitter.com/lecollazo23/status/569344521198276609"
        },
        {
            "retweets": 0,
            "favorites": 1,
            "text": "interior designer branding package on behance includes ipad case business cards desk organizer a",
            "link": "https://twitter.com/CorbinHenry/status/569344507281600514"
        },
        {
            "retweets": 1,
            "favorites": 6,
            "text": "radio turns off even when i close that browser tab why is dual audio streams not possible so much power in ipad so little functionality",
            "link": "https://twitter.com/ryanshrout/status/569344466278072320"
        },
        {
            "retweets": 0,
            "favorites": 1,
            "text": "incorporated inc hopstop transit directions application app for apple for ipad",
            "link": "https://twitter.com/macresslertech/status/569343840110317568"
        },
        {
            "retweets": 0,
            "favorites": 0,
            "text": "xxx movie german amateur bitch gangbanged xxx anal milf ipad usa",
            "link": "https://twitter.com/Leonie184/status/569343034120388608"
        },
        {
            "retweets": 0,
            "favorites": 1,
            "text": "this is awesome astropad transform your ipad into a professional graphics tablet astropad via astropadapp",
            "link": "https://twitter.com/sharpshoot/status/569341582970720257"
        },
        {
            "retweets": 2,
            "favorites": 0,
            "text": "rt check out one of our ios events designed specifically for ipad teachers we feature",
            "link": "https://twitter.com/markwagner/status/569341207417004032"
        },
        {
            "retweets": 0,
            "favorites": 1,
            "text": "my dad dropped his ipad and cracked the screen and is blaming my mom lol can he stop",
            "link": "https://twitter.com/usagijjk/status/569340901438271488"
        },
        {
            "retweets": 0,
            "favorites": 0,
            "text": "go filliw these people right now and i will put your nane in to win tomorrows ipad air zaenallaedun ariellebraps xciannadancerx",
            "link": "https://twitter.com/xCianna_Dancerx/status/569340857779757056"
        },
        {
            "retweets": 0,
            "favorites": 1,
            "text": "affordabienash lustingcameron true but my ipad has no battery and im using my moms phone lmao",
            "link": "https://twitter.com/alrightval/status/569340493697568769"
        },
        {
            "retweets": 0,
            "favorites": 1,
            "text": "playing lords of waterdeep on ipad really enjoying it may have to buy the physical version soon",
            "link": "https://twitter.com/CloakAndMeeple/status/569340092688379904"
        },
        {
            "retweets": 2,
            "favorites": 6,
            "text": "i really dont like how little kids these days can only eat if they have an ipad infront of them i feel thats terrible parenting",
            "link": "https://twitter.com/russellsidhu2/status/569339814522155008"
        },
        {
            "retweets": 2,
            "favorites": 9,
            "text": "my little brother is a huge fan of kennywill he even has him on his ipad background pictwittercomzzpxtuog",
            "link": "https://twitter.com/jessicalucero11/status/569339712483168256"
        },
        {
            "retweets": 0,
            "favorites": 1,
            "text": "haleyy okay wait wait let me charge my ipad real quick i have the best photo",
            "link": "https://twitter.com/Sing_Dance_Act_/status/569339290380939265"
        },
        {
            "retweets": 0,
            "favorites": 0,
            "text": "xxx movie german amateur bitch gangbanged xxx anal milf ipad usa",
            "link": "https://twitter.com/born_serve/status/569339149561565184"
        },
        {
            "retweets": 0,
            "favorites": 0,
            "text": "gleekymccurdy hi im a musician please give feedback to my music win an ipad rt",
            "link": "https://twitter.com/prakharrudro2/status/569339000122707970"
        },
        {
            "retweets": 0,
            "favorites": 3,
            "text": "my mom got braxton and charli an ipad ive never had one neverbeenthefavorite",
            "link": "https://twitter.com/jord_nelson/status/569338986746880000"
        },
        {
            "retweets": 0,
            "favorites": 1,
            "text": "bruh i really need a new ipad pictwittercomocawjdfv",
            "link": "https://twitter.com/itsmyaandmiguel/status/569338753572954112"
        },
        {
            "retweets": 0,
            "favorites": 0,
            "text": "saf u edition uitalia download our free u iphone and ipad app pls rt",
            "link": "https://twitter.com/S_Apps_Factory/status/569338352987713536"
        },
        {
            "retweets": 1,
            "favorites": 1,
            "text": "according to my spam folder im fat and need a bigger penis happy that i won ipads and hot women in my area still want to date me tho",
            "link": "https://twitter.com/LindsayRuggles/status/569337988443967488"
        },
        {
            "retweets": 0,
            "favorites": 0,
            "text": "being a modern media consumer is dangerous while streaming netflix in bed i just dropped my ipad onto my face and cut my lip ouch",
            "link": "https://twitter.com/PolitiCat212/status/569337111272226816"
        },
        {
            "retweets": 0,
            "favorites": 3,
            "text": "astropad transform your ipad into a professional graphics tablet hacker news tech ios apps",
            "link": "https://twitter.com/vishangshah/status/569336237854744576"
        },
        {
            "retweets": 2,
            "favorites": 0,
            "text": "guys look i cant add anyone into a solo group dm with niall since twitter on ipad doesnt have any update on adding people in dms so",
            "link": "https://twitter.com/lciguanlin/status/569336198428168192"
        },
        {
            "retweets": 0,
            "favorites": 2,
            "text": "if you were me where the fuck would you put an ipad",
            "link": "https://twitter.com/kathrynmacdnld/status/569336114747711488"
        },
        {
            "retweets": 3,
            "favorites": 12,
            "text": "jaw line strong as shit ipad big as shit pictwittercomrnnmrtdjb",
            "link": "https://twitter.com/lulgdawgx/status/569335938469535744"
        },
        {
            "retweets": 0,
            "favorites": 1,
            "text": "i entered to win an ipad mini from meandmyhandful freedomevpn privacyisnogame anipadminifromfsecurefreedomecomment",
            "link": "https://twitter.com/lisagee1234/status/569335707933777920"
        },
        {
            "retweets": 0,
            "favorites": 0,
            "text": "xxx movie german amateur bitch gangbanged xxx anal milf ipad usa",
            "link": "https://twitter.com/PerfectBoobs2/status/569335251148935168"
        },
        {
            "retweets": 0,
            "favorites": 3,
            "text": "ipad pictwittercomcwtpltphv",
            "link": "https://twitter.com/xraitax/status/569335232375042048"
        },
        {
            "retweets": 0,
            "favorites": 1,
            "text": "oops wrong video linkhere on youtube wavestation glitch patch my ipad orientation was wrong for video capture",
            "link": "https://twitter.com/MckayGarner/status/569334729717075969"
        },
        {
            "retweets": 0,
            "favorites": 3,
            "text": "proud new owner of a beautiful golden ipad thanks to the greatest parents ever",
            "link": "https://twitter.com/erinblack1738/status/569334526972813312"
        },
        {
            "retweets": 38,
            "favorites": 93,
            "text": "altos adventure is a great ipad snowboarding game pictwittercomcvpebaox",
            "link": "https://twitter.com/verge/status/569334064659869696"
        },
        {
            "retweets": 0,
            "favorites": 4,
            "text": "on his ipad pictwittercomqfyyfx",
            "link": "https://twitter.com/kelz123456789/status/569333311522377729"
        },
        {
            "retweets": 0,
            "favorites": 0,
            "text": "xxx movie german amateur bitch gangbanged xxx anal milf ipad usa",
            "link": "https://twitter.com/BeautifulFemal/status/569333174305738753"
        },
        {
            "retweets": 1,
            "favorites": 1,
            "text": "ireading after ipad initiative failure school supe says la cant buy computers for all by megangeuss arstechnica",
            "link": "https://twitter.com/wfryer/status/569332238443278338"
        },
        {
            "retweets": 1,
            "favorites": 1,
            "text": "you the iphone killer rt cheangotcreez phone fucked up again so im using this ipad man smh",
            "link": "https://twitter.com/Cahnail/status/569332159481315328"
        },
        {
            "retweets": 3,
            "favorites": 3,
            "text": "skaffl mobile learning platform for to ipad classrooms designed by teachers skaffl edtech ipaded e",
            "link": "https://twitter.com/ClassTechTips/status/569332038945406976"
        },
        {
            "retweets": 0,
            "favorites": 1,
            "text": "bit of classic fm in the car on the way home drivers got cruise control set hotspot the camera to the ipad check these pics",
            "link": "https://twitter.com/Missrepresent/status/569331954778279936"
        },
        {
            "retweets": 0,
            "favorites": 4,
            "text": "my mom calls her ipad the candy crush machine lol",
            "link": "https://twitter.com/hiangelali/status/569331079074750465"
        },
        {
            "retweets": 0,
            "favorites": 4,
            "text": "my ya old cousin saved my name into her ipad but forgot the n in my last name",
            "link": "https://twitter.com/lynhvng/status/569330802477002753"
        },
        {
            "retweets": 5,
            "favorites": 8,
            "text": "rt jdelaneyjoann blooms ipad wheel edchat stedchat pictwittercomuqfjnewxn",
            "link": "https://twitter.com/MelissaSeco/status/569330263920152577"
        },
        {
            "retweets": 0,
            "favorites": 2,
            "text": "learn how to use book creator for ipad ukedchat edchat",
            "link": "https://twitter.com/ICTEvangelist/status/569330168516489216"
        },
        {
            "retweets": 1,
            "favorites": 1,
            "text": "traonna because its connected to her phone so if the ipad dont pick up itll go to hers",
            "link": "https://twitter.com/__hawaa_/status/569330060030664704"
        },
        {
            "retweets": 0,
            "favorites": 4,
            "text": "somebody tell me why hes sitting here reading on his ipad at a concert pictwittercomrenbsftyoa",
            "link": "https://twitter.com/LaLaFlamme/status/569329790785867776"
        },
        {
            "retweets": 1,
            "favorites": 2,
            "text": "lizzyroque l she has my ipad fuckk lmao",
            "link": "https://twitter.com/tristandaran/status/569329733437149184"
        },
        {
            "retweets": 4,
            "favorites": 25,
            "text": "so i bought gone girl the book on my ipad but in danish goodworkwilson",
            "link": "https://twitter.com/calbo/status/569328840104742913"
        },
        {
            "retweets": 0,
            "favorites": 2,
            "text": "relationship status my ipad and i are getting pretty serious",
            "link": "https://twitter.com/PrsnPrincess/status/569328688917024768"
        },
        {
            "retweets": 2,
            "favorites": 4,
            "text": "au ipad mini ipad air communicationblogspotcomauipadminiipadairhtmlspreftw",
            "link": "https://twitter.com/KeitaiBancho/status/569327503342313475"
        },
        {
            "retweets": 0,
            "favorites": 1,
            "text": "wufanonly hi im a musician please give feedback to my music win an ipad rt",
            "link": "https://twitter.com/belabose2/status/569327339127115776"
        },
        {
            "retweets": 0,
            "favorites": 1,
            "text": "hattiepearson im doing the most hipster thing imaginable watching mogwai from the music festival on my ipad ignoring they have exist",
            "link": "https://twitter.com/WillGav/status/569327263541563392"
        },
        {
            "retweets": 0,
            "favorites": 1,
            "text": "i hate having to update my iphone or ipad",
            "link": "https://twitter.com/jenni_reyes8/status/569326398046912512"
        },
        {
            "retweets": 13,
            "favorites": 11,
            "text": "rt jfklibrary the jfk challenge scappenger hunt for families starts monday play for a chance to win an ipad mini pictwittercomdknylpn",
            "link": "https://twitter.com/USNatArchives/status/569325739570561024"
        },
        {
            "retweets": 3,
            "favorites": 0,
            "text": "ipad iphone and ipod skins from florals by fred zazzle gift",
            "link": "https://twitter.com/FotosFred/status/569325732704464896"
        },
        {
            "retweets": 2,
            "favorites": 1,
            "text": "iambett check out my new youtube video leak release please called octave made on an ipad",
            "link": "https://twitter.com/The_real_bobo4/status/569325654077894656"
        },
        {
            "retweets": 1,
            "favorites": 1,
            "text": "im obsessed with cookie jam like i play it on my macbook ipad and iphone when i run out of lives",
            "link": "https://twitter.com/B0NNIE_B00/status/569325184936759296"
        },
        {
            "retweets": 2,
            "favorites": 5,
            "text": "google play music app coming to ipad",
            "link": "https://twitter.com/gmanews/status/569323238171418624"
        },
        {
            "retweets": 0,
            "favorites": 1,
            "text": "apps to let students create their own content ipad apps edtech edchat",
            "link": "https://twitter.com/dionGnorman/status/569323207372759042"
        },
        {
            "retweets": 0,
            "favorites": 0,
            "text": "creeracity new purple leopard auto sleepwake function degree rotating smart case cover for ipad air gen eu",
            "link": "https://twitter.com/Tabletolic/status/569322742597595137"
        },
        {
            "retweets": 0,
            "favorites": 2,
            "text": "fuck you and give me my fucking ipad back",
            "link": "https://twitter.com/flirthyojong/status/569322654987132928"
        },
        {
            "retweets": 0,
            "favorites": 0,
            "text": "xxx movie german amateur bitch gangbanged xxx anal milf ipad usa",
            "link": "https://twitter.com/born_serve/status/569321789018509312"
        },
        {
            "retweets": 0,
            "favorites": 0,
            "text": "elbblick spin doctors puh auf ipad luft das dort twitbar",
            "link": "https://twitter.com/Coocooo266/status/569319993931931648"
        },
        {
            "retweets": 0,
            "favorites": 0,
            "text": "android ledger pctop riotous alternatives into ipad pdlfi",
            "link": "https://twitter.com/AldridgeRichar3/status/569318357519855617"
        },
        {
            "retweets": 0,
            "favorites": 0,
            "text": "xxx movie german amateur bitch gangbanged xxx anal milf ipad usa",
            "link": "https://twitter.com/PerfectBoobs2/status/569318343225831424"
        },
        {
            "retweets": 8,
            "favorites": 10,
            "text": "quick update on our game bounce were now top for both iphone and ipad also just launched on google play",
            "link": "https://twitter.com/trey_smith/status/569317821068521472"
        },
        {
            "retweets": 1,
            "favorites": 4,
            "text": "sharing this with our school asap cool tool jdelaneyjoann blooms ipad wheel edchat stedchat pictwittercomozfsfqzp",
            "link": "https://twitter.com/rachealburden/status/569317748875988993"
        },
        {
            "retweets": 1,
            "favorites": 1,
            "text": "the video i just found of court on my ipad from earlier",
            "link": "https://twitter.com/knappy98/status/569317612758409216"
        },
        {
            "retweets": 11,
            "favorites": 23,
            "text": "the ipad when i was younger",
            "link": "https://twitter.com/TheePerfectBF/status/569317278015217665"
        },
        {
            "retweets": 0,
            "favorites": 4,
            "text": "my phone broke so if you need to contact me text me in my ipad cailinmcicloudcom",
            "link": "https://twitter.com/cailinmc17/status/569317071877750784"
        },
        {
            "retweets": 0,
            "favorites": 0,
            "text": "xxx movie german amateur bitch gangbanged xxx anal milf ipad usa",
            "link": "https://twitter.com/BeautifulFemal/status/569316911869255680"
        },
        {
            "retweets": 5,
            "favorites": 3,
            "text": "whaaat youtube this guys got a magic ipad pictwittercomazmnqjiz",
            "link": "https://twitter.com/2013tabu/status/569316761922744321"
        },
        {
            "retweets": 0,
            "favorites": 0,
            "text": "iphone ipad appstore preissenkung perfect photo statt",
            "link": "https://twitter.com/AppTicker/status/569316284300693504"
        },
        {
            "retweets": 3,
            "favorites": 2,
            "text": "using ipad in science part via deepexperience edtech ipaded",
            "link": "https://twitter.com/riley_ed/status/569315929655525376"
        },
        {
            "retweets": 3,
            "favorites": 1,
            "text": "new cases reveal ipad pros inch form factor ipadpro ipad apple",
            "link": "https://twitter.com/iPhoneHackx/status/569315672783777792"
        },
        {
            "retweets": 8,
            "favorites": 0,
            "text": "apple made for iphone anker usb iphone ipad ipod pictwittercomqdhslidqx",
            "link": "https://twitter.com/Bestseller_Navi/status/569315650104983552"
        },
        {
            "retweets": 0,
            "favorites": 1,
            "text": "my ipad is on but i dont want to stop watching gameofthrones to charge it",
            "link": "https://twitter.com/NikiLuv73/status/569314865275404288"
        },
        {
            "retweets": 0,
            "favorites": 3,
            "text": "my future children wont be glued to an ipad or some technology all day like children are these days gooutside",
            "link": "https://twitter.com/sarita_faith/status/569313452352614401"
        },
        {
            "retweets": 22,
            "favorites": 28,
            "text": "mpimiddle blooms ipad wheel edchat stedchat pictwittercomdkhygyisf",
            "link": "https://twitter.com/dpriester/status/569313224660783104"
        },
        {
            "retweets": 0,
            "favorites": 0,
            "text": "xxx movie german amateur bitch gangbanged xxx anal milf ipad usa",
            "link": "https://twitter.com/GirlLatingirl/status/569312970959941632"
        },
        {
            "retweets": 1,
            "favorites": 1,
            "text": "anasf check out my new youtube video leak release please called octave made on an ipad",
            "link": "https://twitter.com/The_real_bobo4/status/569312939443773440"
        },
        {
            "retweets": 0,
            "favorites": 4,
            "text": "im on my ipad where i cant tweet videos my legs are paralyzed i can not post the video",
            "link": "https://twitter.com/loverIucy/status/569312828529602561"
        },
        {
            "retweets": 14,
            "favorites": 1,
            "text": "sa hindi marunong magpalit ng dp sa ipad i hope this helps we support xianlim pictwittercomclxebdyd",
            "link": "https://twitter.com/Niorapaengeol/status/569312766940618753"
        },
        {
            "retweets": 0,
            "favorites": 3,
            "text": "ipad pictwittercomicviypev",
            "link": "https://twitter.com/loveitno3/status/569311615603970049"
        },
        {
            "retweets": 0,
            "favorites": 0,
            "text": "apple ipad air st generation gb wifi in silver ipadair",
            "link": "https://twitter.com/iPadAirsales/status/569311565264125953"
        },
        {
            "retweets": 13,
            "favorites": 16,
            "text": "apples dirty little rare earth secret aapl iphone ipad ios mac applewatch applecarpictwittercomjtymmsgv",
            "link": "https://twitter.com/AppleReporter/status/569310958348161026"
        },
        {
            "retweets": 0,
            "favorites": 6,
            "text": "landfebruary finally abstracted norwich market photo using ipad procreate looks best viewed as a tiny tiny pic pictwittercomziwaevanf",
            "link": "https://twitter.com/teresacutmore/status/569310099946270721"
        },
        {
            "retweets": 3,
            "favorites": 12,
            "text": "i go on my ipad and my mom was reading an article about how to deal with teenagers",
            "link": "https://twitter.com/_jessicanoriel/status/569308660465324032"
        },
        {
            "retweets": 0,
            "favorites": 0,
            "text": "xxx movie german amateur bitch gangbanged xxx anal milf ipad usa",
            "link": "https://twitter.com/Melanie6ix/status/569308329538936833"
        },
        {
            "retweets": 17,
            "favorites": 0,
            "text": "whats on your ipad alora i was hooked from the first scene and couldnt stop reading cru artknb bynr iartg",
            "link": "https://twitter.com/TamieDearen/status/569307521548038144"
        },
        {
            "retweets": 0,
            "favorites": 0,
            "text": "hf beam antenna calculator iphone ipod app hamradio ipad",
            "link": "https://twitter.com/iPhoneAppDeal/status/569303841344106496"
        },
        {
            "retweets": 0,
            "favorites": 0,
            "text": "iphone ipad appstore preissenkung distant sunsmax touch the sky own the universe statt",
            "link": "https://twitter.com/AppTicker/status/569300922582609921"
        },
        {
            "retweets": 6,
            "favorites": 8,
            "text": "happy th birthday blokes talking tech years of podcasting with my mate stephenfenech on ep we talked ipad vodafail ps more",
            "link": "https://twitter.com/trevorlong/status/569300035982139394"
        },
        {
            "retweets": 0,
            "favorites": 0,
            "text": "microsoft corporation microsoft onenote for ipad itunes",
            "link": "https://twitter.com/marioamartinezr/status/569299929828605952"
        },
        {
            "retweets": 0,
            "favorites": 0,
            "text": "xxx movie german amateur bitch gangbanged xxx anal milf ipad usa",
            "link": "https://twitter.com/BeautifulFemal/status/569298966015299585"
        },
        {
            "retweets": 0,
            "favorites": 8,
            "text": "never wanna use my yo brothers ipad again after i opened it there was a vine of a girl twerking in booty shorts",
            "link": "https://twitter.com/TeamSeaman/status/569298671923277824"
        },
        {
            "retweets": 0,
            "favorites": 0,
            "text": "langelier saturation index calculator lsi iphone water ipad app",
            "link": "https://twitter.com/iPhoneAppDeal/status/569298323191902208"
        },
        {
            "retweets": 0,
            "favorites": 3,
            "text": "grow your account and succeed on twitter try justunfollow now also on ipad",
            "link": "https://twitter.com/TylerLAflac/status/569297788531544065"
        },
        {
            "retweets": 0,
            "favorites": 14,
            "text": "its so hard on an ipad you needa use two fingers",
            "link": "https://twitter.com/alohtae/status/569296935711977472"
        },
        {
            "retweets": 0,
            "favorites": 4,
            "text": "sets phoneipadlaptop wallpaper as harry potter related things in the year its fine im fine",
            "link": "https://twitter.com/juhoseoks/status/569295941498331136"
        },
        {
            "retweets": 0,
            "favorites": 2,
            "text": "i just downloaded the movie the imitation game to my ipad for free movie box app in cydia",
            "link": "https://twitter.com/PuckFolice/status/569295799869431808"
        },
        {
            "retweets": 0,
            "favorites": 2,
            "text": "amybrewis upload to drive open in imovie on ipad to edit and then upload to youtube from ipad i use youtube capture",
            "link": "https://twitter.com/gregkulowiec/status/569295086195904512"
        },
        {
            "retweets": 1,
            "favorites": 2,
            "text": "wshhh nsm j attaqu clash of clan mon ipad c eteint",
            "link": "https://twitter.com/imFizk/status/569294884248662016"
        },
        {
            "retweets": 0,
            "favorites": 3,
            "text": "google play music app coming to ipad",
            "link": "https://twitter.com/gmanewsbreaking/status/569294879794143235"
        },
        {
            "retweets": 0,
            "favorites": 0,
            "text": "generalberholtes ipad mit retina display gb wifi wei generation fdfda",
            "link": "https://twitter.com/AppleRefurb_DE/status/569294840481128449"
        },
        {
            "retweets": 1,
            "favorites": 0,
            "text": "three tips for apples keynote app on ipad macintosh",
            "link": "https://twitter.com/macintosh_dp/status/569293686833606656"
        },
        {
            "retweets": 1,
            "favorites": 5,
            "text": "why is my dad watching the superbowl halftime katy perry performance on his ipad rn",
            "link": "https://twitter.com/Christkrantz/status/569291257391882241"
        },
        {
            "retweets": 0,
            "favorites": 6,
            "text": "astropad transforms your ipad into a true graphics astropadtransformsipadtruegraphicstablethtml wacom graphitablet graphicdesign tech webdesign design",
            "link": "https://twitter.com/dreambugdesigns/status/569291223443378176"
        },
        {
            "retweets": 0,
            "favorites": 0,
            "text": "apple ipad mini st generation gb wifi in black wlogitech keyboard generation x gen x",
            "link": "https://twitter.com/generationx_age/status/569290608642289667"
        },
        {
            "retweets": 0,
            "favorites": 0,
            "text": "responsive layouts lassen websites vom iphoneipaddesktoppc gut aussehen und per maustouch optimal bedienen",
            "link": "https://twitter.com/power4soul/status/569289973788217344"
        },
        {
            "retweets": 0,
            "favorites": 0,
            "text": "emperorleather crafterei ipad air hlletasche amarettini pictwittercomducwerej",
            "link": "https://twitter.com/EmperorLeather/status/569289912945651713"
        },
        {
            "retweets": 4,
            "favorites": 5,
            "text": "congratulations mabrewer winneripad mini from toyotaofrockwall edcampawesome cisdtigers zachsnow stuartburtpictwittercomqfvxesccu",
            "link": "https://twitter.com/gunnels5G/status/569289691545014272"
        },
        {
            "retweets": 0,
            "favorites": 0,
            "text": "ive harvested of food ipad ipadgames gameinsight",
            "link": "https://twitter.com/IvanaKocifajova/status/569285465695768577"
        },
        {
            "retweets": 0,
            "favorites": 0,
            "text": "ive collected gold coins ipad ipadgames gameinsight",
            "link": "https://twitter.com/IvanaKocifajova/status/569285465649627136"
        },
        {
            "retweets": 0,
            "favorites": 0,
            "text": "support is it my fault that the ipad app for twitter always crashes when i try to upload an panorama picture as a header thx",
            "link": "https://twitter.com/Appleaner/status/569285463372120065"
        },
        {
            "retweets": 0,
            "favorites": 0,
            "text": "i got a reward light my fire gameinsight ipadgames ipad",
            "link": "https://twitter.com/DDudely/status/569285460368842752"
        },
        {
            "retweets": 0,
            "favorites": 0,
            "text": "today deals on adonit jot touch for ipad ipad air ipad mini",
            "link": "https://twitter.com/teemtrend/status/569285457768361984"
        },
        {
            "retweets": 0,
            "favorites": 0,
            "text": "i have clue multiplier and its much easier to play now ipad ipadgames gameinsight",
            "link": "https://twitter.com/lydiaconard21/status/569285457172959232"
        },
        {
            "retweets": 0,
            "favorites": 0,
            "text": "man i wish i could get the ipad from my year old sister siblings",
            "link": "https://twitter.com/Cameron_Penney1/status/569285455599919104"
        },
        {
            "retweets": 0,
            "favorites": 1,
            "text": "we love ipad time using them with math centers is even better pictwittercomkpizdtwjr",
            "link": "https://twitter.com/duckettsclass/status/569285452055728128"
        },
        {
            "retweets": 0,
            "favorites": 0,
            "text": "i can go alices room have you already discovered this location ipad ipadgames gameinsight",
            "link": "https://twitter.com/TamdhTammy/status/569285448532676608"
        },
        {
            "retweets": 0,
            "favorites": 0,
            "text": "detectives belongings is a wonderful collection envy me and complete it too ipad ipadgames game",
            "link": "https://twitter.com/TateWanda/status/569285447668670465"
        },
        {
            "retweets": 0,
            "favorites": 0,
            "text": "xxx movie put those hard cocks inside my wet hairy pussy xxx anal milf ipad usa",
            "link": "https://twitter.com/Lesbianlovers7/status/569285439900794880"
        }
    ]
}