{
    "2016-01-31": [
        {
            "retweets": 1,
            "favorites": 4,
            "text": "me okay ben time to turn the ipad off ben its not over me easy there john rambo",
            "link": "https://twitter.com/devlin1/status/693946605376933888"
        },
        {
            "retweets": 8,
            "favorites": 23,
            "text": "jailbreak ios on iphone ipad iosoniphoneipadhtml",
            "link": "https://twitter.com/iPhoneFeedback/status/693945877073924096"
        },
        {
            "retweets": 2,
            "favorites": 6,
            "text": "we constantly test the kuam news app on all types of digital displaysespecially the millionpixel ipad pro pictwittercomweeozcpf",
            "link": "https://twitter.com/kuamnews/status/693945477608308736"
        },
        {
            "retweets": 3,
            "favorites": 16,
            "text": "found this on my ipad i remember playing a game with him first one that cums loses half german half pinoy pictwittercomwarxsiru",
            "link": "https://twitter.com/ChxseDoza/status/693944714521870336"
        },
        {
            "retweets": 4,
            "favorites": 1,
            "text": "buy your nashvillefc membership today and be entered to win a free ipad mini fcmyshopifycom pictwittercomamzqrua",
            "link": "https://twitter.com/NashvilleSC/status/693944501505806338"
        },
        {
            "retweets": 0,
            "favorites": 2,
            "text": "how about this the dessert menu is an ipad in a beautiful wooden case lovemexicopictwittercomsbhiqvos",
            "link": "https://twitter.com/austeni/status/693943153443737601"
        },
        {
            "retweets": 2,
            "favorites": 3,
            "text": "ibooks iphone ipad mac apple books freebie ibooksauthor macbook applenews applestore readmore authoremmalidmt",
            "link": "https://twitter.com/SterlingEmmal20/status/693941768664920065"
        },
        {
            "retweets": 2,
            "favorites": 11,
            "text": "ipad air smart connector ipad air linkman mannetipadipadnews",
            "link": "https://twitter.com/unnot/status/693940390953496576"
        },
        {
            "retweets": 3,
            "favorites": 15,
            "text": "ayer vimos que si hay muchos accesorios para iphone ipad y ms ishopnuevover ishopveracruz ishopxalapa pictwittercomscmjyfwqn",
            "link": "https://twitter.com/Mimacmx/status/693936733168103425"
        },
        {
            "retweets": 5,
            "favorites": 3,
            "text": "lady reign raffle tickets road to raleigh nc tickets are prizes st ipad mini nd rd to buy tickets dm us",
            "link": "https://twitter.com/jaybuckets5/status/693935307280941056"
        },
        {
            "retweets": 0,
            "favorites": 4,
            "text": "lmao meg is texting me off her ipad since she got her phone taken away",
            "link": "https://twitter.com/kateog123/status/693945677446012928"
        },
        {
            "retweets": 1,
            "favorites": 1,
            "text": "englandcordell dont forget your ipad",
            "link": "https://twitter.com/JordanCooper05/status/693944099171340288"
        },
        {
            "retweets": 0,
            "favorites": 3,
            "text": "im never buying an apple product again ipad just burned through megs of data in an hour in standby",
            "link": "https://twitter.com/amarquis32/status/693943764801474560"
        },
        {
            "retweets": 2,
            "favorites": 0,
            "text": "louisahodge heres some ipad vid my old betcamsp would take too long to setup pictwittercompofbkirtm",
            "link": "https://twitter.com/hightheretv/status/693942207359770625"
        },
        {
            "retweets": 0,
            "favorites": 2,
            "text": "my ipad didnt work with photokatsu but i bypassed it and now im in this repair mode menu thingy lol pictwittercomhyceeryz",
            "link": "https://twitter.com/yvesmp3/status/693941981035102209"
        },
        {
            "retweets": 0,
            "favorites": 2,
            "text": "no ipad app yet star pictwittercompyjriipt",
            "link": "https://twitter.com/Objective_Neo/status/693941739481088003"
        },
        {
            "retweets": 1,
            "favorites": 1,
            "text": "thegirlwhoslept shazaaaaaa go to sleep ur gonna get sick put down the goddamned ipad off to bed",
            "link": "https://twitter.com/Nilzii_mzst/status/693941513860952067"
        },
        {
            "retweets": 0,
            "favorites": 3,
            "text": "had a dream in which i had a hacked copy of gta on my ipad but the real version had minigames and dress ups and like winnie the pooh",
            "link": "https://twitter.com/coolbiRdpics/status/693941277453213699"
        },
        {
            "retweets": 0,
            "favorites": 4,
            "text": "my year old niece just told me she deleted all the games on her ipad because she was too good at them",
            "link": "https://twitter.com/empybus/status/693940913668759553"
        },
        {
            "retweets": 1,
            "favorites": 3,
            "text": "translates english arabic with games to make studying fun try arabic dictionary for iphone ipad ithinkdiff",
            "link": "https://twitter.com/QkdkV/status/693940025315201024"
        },
        {
            "retweets": 1,
            "favorites": 0,
            "text": "ipad pro pencil vs wacom cintiq companion pictwittercomgocsuaj",
            "link": "https://twitter.com/jason_boyer/status/693939421163421696"
        },
        {
            "retweets": 0,
            "favorites": 0,
            "text": "top ios news of the week ipad air iphone is tops new microsoft keyboard related articles",
            "link": "https://twitter.com/latest_ooyuz/status/693938556704792576"
        },
        {
            "retweets": 0,
            "favorites": 1,
            "text": "ajjabari nigga had two black eyes and an ipad in his pocket",
            "link": "https://twitter.com/biggy_black/status/693937391761895424"
        },
        {
            "retweets": 1,
            "favorites": 1,
            "text": "grab unlimited books for your kindle sony or ipad only ebooksnethtml contentmo happyreading bookworms",
            "link": "https://twitter.com/MoGalore/status/693937305707347968"
        },
        {
            "retweets": 6,
            "favorites": 25,
            "text": "the feels this game is so timeless absolutely hooked to the ipad version",
            "link": "https://twitter.com/FuntCaseUK/status/693935969964290048"
        },
        {
            "retweets": 6,
            "favorites": 32,
            "text": "im looking up snapchat app from ipad and none of these look like the real app so im confused",
            "link": "https://twitter.com/drayamichele/status/693935045816389632"
        },
        {
            "retweets": 6,
            "favorites": 34,
            "text": "can you get snap chat on ipad",
            "link": "https://twitter.com/drayamichele/status/693934435050205184"
        },
        {
            "retweets": 8,
            "favorites": 5,
            "text": "winners will be announced on rd of feb for amazon vouchers for mini ipad it will be on the th of feb loveourcustomers prizes",
            "link": "https://twitter.com/LocalSprinter/status/693934028727123972"
        },
        {
            "retweets": 0,
            "favorites": 0,
            "text": "apple ipad generation wifi cellular gb schwarz gebraucht onlinecomappleipadgenerationwificellulargbschwarzgebraucht",
            "link": "https://twitter.com/BietenOnline/status/693932900778164224"
        },
        {
            "retweets": 0,
            "favorites": 10,
            "text": "so momdad getting marley a ipad wdatashes used gb of our shared data it doesnt reset for days pictwittercomfrncjtlgfu",
            "link": "https://twitter.com/skyler_reed97/status/693932520526606336"
        },
        {
            "retweets": 1,
            "favorites": 5,
            "text": "hope im taking my kids camping and to the beach not teaching them how to play fruit ninja on the ipad",
            "link": "https://twitter.com/colin_michaelw/status/693930443494838272"
        },
        {
            "retweets": 31,
            "favorites": 119,
            "text": "five years with an ipad and ive never touched my laptop screen a week with an ipad pro and im doing it all the time",
            "link": "https://twitter.com/benedictevans/status/693927272219185152"
        },
        {
            "retweets": 0,
            "favorites": 0,
            "text": "iphone ipad appstore preissenkung a nerds game mathematikquiz statt",
            "link": "https://twitter.com/AppTicker/status/693920417216610304"
        },
        {
            "retweets": 4,
            "favorites": 7,
            "text": "ibooks storeiphoneipadipod touchios ipodcomibooksstoreiosuserguideiphoneipadipodtouchhtml pictwittercomhatfjckg",
            "link": "https://twitter.com/iArigato/status/693916113634140160"
        },
        {
            "retweets": 0,
            "favorites": 0,
            "text": "apple ipad mini st generation gb wifi in white silver ipadministgenerationgbwifiinwhitesilver pictwittercombspwzembrb",
            "link": "https://twitter.com/DigitalDealerCo/status/693914877291696129"
        },
        {
            "retweets": 3,
            "favorites": 5,
            "text": "rode videomic me android mobile tablets apple ipads or windows phones video rodemicspictwittercombuevmjtti",
            "link": "https://twitter.com/GaryDmedia/status/693913996479475712"
        },
        {
            "retweets": 0,
            "favorites": 0,
            "text": "hab mal die boobs einer patientin mit diesem ipad fotografiert sie hat mich verarscht pictwittercomkcdsiekb",
            "link": "https://twitter.com/KingAFB/status/693911119681949696"
        },
        {
            "retweets": 4,
            "favorites": 3,
            "text": "iphoneipad users never miss an episode of the paranormal podcast subscribe free pls rt podcastjimharoldid",
            "link": "https://twitter.com/THEJimHarold/status/693910909232750592"
        },
        {
            "retweets": 0,
            "favorites": 0,
            "text": "ipad air case deutet auf vier lautsprecher blitz und smart connector fotos aircasefotos pictwittercomrfivlryc",
            "link": "https://twitter.com/macerkopf_de/status/693896370357428229"
        },
        {
            "retweets": 10,
            "favorites": 60,
            "text": "i could probably be arsed to play clever puzzles on an ipad but not like in a giant floralass landscape on the big pc",
            "link": "https://twitter.com/leighalexander/status/693889511613468673"
        },
        {
            "retweets": 0,
            "favorites": 0,
            "text": "produktiv sein mit dem ipad geektalkch aspictwittercomonugjxn",
            "link": "https://twitter.com/pokipsieblog/status/693887067852521472"
        },
        {
            "retweets": 63,
            "favorites": 61,
            "text": "the ipad pro and apple pencil combination is unexpectedly winning over professional artists pictwittercomqnprxfwu",
            "link": "https://twitter.com/ForbesTech/status/693863819450392578"
        },
        {
            "retweets": 6,
            "favorites": 48,
            "text": "andreaschoice this is so cute on your snap your cat playing on your ipad i cant pictwittercomufnasgmv",
            "link": "https://twitter.com/Lozza_bae/status/693858794430971905"
        },
        {
            "retweets": 0,
            "favorites": 0,
            "text": "apple ipad st generation gb wifi in silverblack via ebay ipad rtpictwittercomradqkopb",
            "link": "https://twitter.com/giantshoppercom/status/693858040693530625"
        },
        {
            "retweets": 0,
            "favorites": 0,
            "text": "top apple ipad wei gb entsperrt wifi mit ovp case gold onlinecomtopappleipadweissgbentsperrtwifimitovpcasegold",
            "link": "https://twitter.com/BietenOnline/status/693854330877677568"
        },
        {
            "retweets": 0,
            "favorites": 10,
            "text": "lauren is that terrible friend that plays loud videos on her ipad when youre trying to watch a movie",
            "link": "https://twitter.com/CentenoMaggy/status/693854269942927360"
        },
        {
            "retweets": 0,
            "favorites": 0,
            "text": "symmetrain by black pants studio gmbh ahora gratis para ipad en la app store download via",
            "link": "https://twitter.com/VissioApps/status/693853977784537088"
        },
        {
            "retweets": 4,
            "favorites": 7,
            "text": "never been funded ncteacher days left on donorschoose project ipad minis to makeadifference in reading raktogrowreadingandmathchallengeid",
            "link": "https://twitter.com/SHEILAMCHONE/status/693853883270074368"
        },
        {
            "retweets": 50,
            "favorites": 117,
            "text": "inmychildhoodbedroom this was my ipad pictwittercomorvlaswt",
            "link": "https://twitter.com/tonysheps/status/693851139268317184"
        },
        {
            "retweets": 0,
            "favorites": 0,
            "text": "apple ipad mini st generation gb wifi in white silver ipadministgenerationgbwifiinwhitesilver pictwittercomtgjhayii",
            "link": "https://twitter.com/DigitalDealerCo/status/693848646039654400"
        },
        {
            "retweets": 0,
            "favorites": 3,
            "text": "sunrise dec th oulu hmeenjrvi finland sunset lake frozen mestapaikka landscape landscapes ipad pictwittercomztzpahx",
            "link": "https://twitter.com/SampsaKettunen/status/693846329949319168"
        },
        {
            "retweets": 1,
            "favorites": 3,
            "text": "can i just say my ipad slayss pictwittercompnibyrkw",
            "link": "https://twitter.com/cierramaemoore/status/693845643194941441"
        },
        {
            "retweets": 0,
            "favorites": 4,
            "text": "breagan got her ipad a month ago and already has storage",
            "link": "https://twitter.com/_bryleeee/status/693845010052067328"
        },
        {
            "retweets": 0,
            "favorites": 2,
            "text": "on ipad get smart notebook app load z to get an az template sshot any xword enjoypictwittercommcujkuu",
            "link": "https://twitter.com/jmarquisdpcdsb/status/693844332852420608"
        },
        {
            "retweets": 4,
            "favorites": 0,
            "text": "ipad air smart connector ipad pro pictwittercomsmxerh",
            "link": "https://twitter.com/komilavochnikov/status/693843974990225408"
        },
        {
            "retweets": 2,
            "favorites": 2,
            "text": "how to use find my iphone to locate stolen iphone pictwittercomxatpswrdoh iphone ipad via myapplegadgets",
            "link": "https://twitter.com/iGadgetLady/status/693843937220390912"
        },
        {
            "retweets": 47,
            "favorites": 62,
            "text": "ipad air cases to fit four speakers rear flash and smart connector appear aircasesleak by eslivka pictwittercompnefymbtf",
            "link": "https://twitter.com/MacRumors/status/693842953278615552"
        },
        {
            "retweets": 0,
            "favorites": 0,
            "text": "iphone ipad appstore pricedrop mein bersetzer pro from to",
            "link": "https://twitter.com/AppTicker_COM/status/693838662136651778"
        },
        {
            "retweets": 0,
            "favorites": 0,
            "text": "mein neuer erfolg in mystery manor perpetuum mobile ipad ipadgames gameinsight",
            "link": "https://twitter.com/Yovaik/status/693837256507944960"
        },
        {
            "retweets": 0,
            "favorites": 0,
            "text": "udid aktivierung ios xbeta fr iphone ipad apple watch support onlinecomudidaktivierungiosxbetafueriphoneipadapplewatchsupport",
            "link": "https://twitter.com/BietenOnline/status/693836001601413121"
        },
        {
            "retweets": 1,
            "favorites": 2,
            "text": "best practice webinar ein praxiserprobter ipad workflow fr das klassenzimmer pictwittercomypxrlsxjmq",
            "link": "https://twitter.com/wagjuer/status/693835706712596481"
        },
        {
            "retweets": 0,
            "favorites": 2,
            "text": "webinar das ipad als mobiles filmstudio im unterricht globinar schaeferkbbzpictwittercomwihqwt",
            "link": "https://twitter.com/wagjuer/status/693834430377529345"
        },
        {
            "retweets": 0,
            "favorites": 0,
            "text": "huawei watch anker usb hub bluetooth headphones and more immer wieder sonntags kw das ipad auf den mars bringen mittagspause",
            "link": "https://twitter.com/SnackpackWayne/status/693832530018078722"
        },
        {
            "retweets": 0,
            "favorites": 0,
            "text": "apple ipad mini st generation gb wifi in white silver ipadministgenerationgbwifiinwhitesilver pictwittercomjkaahcuy",
            "link": "https://twitter.com/DigitalDealerCo/status/693829409745207297"
        },
        {
            "retweets": 0,
            "favorites": 0,
            "text": "gutschein sonntagsdeal apple ipad mini smart cover apple ipad mini smart cover pu blau und grn nur am",
            "link": "https://twitter.com/Preisrabatte/status/693829278949994496"
        },
        {
            "retweets": 0,
            "favorites": 0,
            "text": "gutschein sonntagsdeal wacom intuos creative stylus wacom intuos creative stylus fr ipad ipad mini",
            "link": "https://twitter.com/Preisrabatte/status/693829278165630976"
        },
        {
            "retweets": 0,
            "favorites": 0,
            "text": "apple ipad air st generation gb wifi g verizon in silver plus bundle ipadair",
            "link": "https://twitter.com/iPadAirsales/status/693824884670078976"
        },
        {
            "retweets": 0,
            "favorites": 0,
            "text": "apple ipad apple ipad mini st generation gb tablet ereader",
            "link": "https://twitter.com/NYCGlobalBrands/status/693822703556386817"
        },
        {
            "retweets": 17,
            "favorites": 31,
            "text": "somewhere someones kids are playing on an ipad so that their parent can pen an oped about why robots shouldnt take care of kids",
            "link": "https://twitter.com/rcalo/status/693817422097199105"
        },
        {
            "retweets": 0,
            "favorites": 0,
            "text": "apple ipad mini st generation gb wifi in white silver bundle ipadministgenerationgbwifiinwhitesilverbundle pictwittercomdpdqvog",
            "link": "https://twitter.com/DigitalDealerCo/status/693817224650297345"
        },
        {
            "retweets": 75,
            "favorites": 0,
            "text": "touch run games arcade ipad app free arcade",
            "link": "https://twitter.com/amyrightside/status/693815055687815168"
        },
        {
            "retweets": 75,
            "favorites": 0,
            "text": "whatspad web social networking entertainment ipad app socialnetworking",
            "link": "https://twitter.com/amyrightside/status/693815054895071232"
        },
        {
            "retweets": 0,
            "favorites": 0,
            "text": "iphone ipad appstore preissenkung tumble experiments statt",
            "link": "https://twitter.com/AppTicker/status/693814354580475904"
        },
        {
            "retweets": 4,
            "favorites": 12,
            "text": "ipad bort psshare jajptidcusa pictwittercomdurkusc",
            "link": "https://twitter.com/en_________/status/693814161076137984"
        },
        {
            "retweets": 2,
            "favorites": 7,
            "text": "using seesaw for ipad work assessmentevidence video tutorial edtech ipaded elearningpictwittercomfefiadxpy",
            "link": "https://twitter.com/iLearn2Primary/status/693813423755366400"
        },
        {
            "retweets": 32,
            "favorites": 13,
            "text": "giveaway time win your self a free ipad mini all you have to do is like our facebook page and rtpictwittercomcoadkpwcbg",
            "link": "https://twitter.com/LocalSprinter/status/693807474990804992"
        },
        {
            "retweets": 0,
            "favorites": 9,
            "text": "ouch my work ipad just attacked me who says anchoring isnt a dangerous job lol newspictwittercombvvdhwml",
            "link": "https://twitter.com/KrisAndersonTV/status/693806385738440707"
        },
        {
            "retweets": 11,
            "favorites": 4,
            "text": "state dept records show john kerry sent hillary a secret email from his ipad deptrecordsshowjohnkerrysenthillaryasecretemailfromhisipad instapundit adambaldwin amymek",
            "link": "https://twitter.com/BoboFromTexas/status/693805859579654144"
        },
        {
            "retweets": 2,
            "favorites": 78,
            "text": "marcirl kappische i dropped a first generation ipad on my face in bed once",
            "link": "https://twitter.com/notch/status/693805274797309953"
        },
        {
            "retweets": 0,
            "favorites": 0,
            "text": "ich starte ein raumschiff in meiner airport city ipad ipadgames gameinsight",
            "link": "https://twitter.com/eberlmeister/status/693804573429993472"
        },
        {
            "retweets": 0,
            "favorites": 0,
            "text": "iphone ipad appstore preissenkung gratitude journal the original statt",
            "link": "https://twitter.com/AppTicker/status/693798259903578114"
        },
        {
            "retweets": 0,
            "favorites": 0,
            "text": "temperierter glass ipad mini schutz screen protector onlinecomtemperierterglassipadminischutzscreenprotector",
            "link": "https://twitter.com/BietenOnline/status/693797293175083008"
        },
        {
            "retweets": 29,
            "favorites": 76,
            "text": "imagine if ios apps continued with the innovation that tweetie for ipad and our choice pioneered years ago i feel like all that is gone",
            "link": "https://twitter.com/flyosity/status/693795804981678082"
        },
        {
            "retweets": 0,
            "favorites": 0,
            "text": "apple ipad mini st generation gb wifi in white silver ipadministgenerationgbwifiinwhitesilver pictwittercomlnsmgyvq",
            "link": "https://twitter.com/DigitalDealerCo/status/693793185999368192"
        },
        {
            "retweets": 0,
            "favorites": 0,
            "text": "apple ipad mini st generation gb wifi in white silver ipadministgenerationgbwifiinwhitesilver pictwittercomzssgenzw",
            "link": "https://twitter.com/DigitalDealerCo/status/693788055254093824"
        },
        {
            "retweets": 0,
            "favorites": 0,
            "text": "mein enthusiastisches surface review ipad pro oder surface",
            "link": "https://twitter.com/ekston/status/693783866084081666"
        },
        {
            "retweets": 15,
            "favorites": 55,
            "text": "new video how to install cinema box free ios no jailbreak no crashing iphone ipad ipod touch",
            "link": "https://twitter.com/DinoD7/status/693781491478851586"
        },
        {
            "retweets": 0,
            "favorites": 0,
            "text": "telmi dewa high tech google pixel c das neue tablet ist kein ipad killer",
            "link": "https://twitter.com/payudaraputing/status/693766190733201408"
        },
        {
            "retweets": 0,
            "favorites": 0,
            "text": "marine cft and pft scores calculators usmc military app iphone ipad",
            "link": "https://twitter.com/iPhoneAppDeal/status/693745710689157120"
        },
        {
            "retweets": 0,
            "favorites": 0,
            "text": "ipad air kdisplaytechnologie und gb ram wahrscheinlich airapplekdisplaynewshtml",
            "link": "https://twitter.com/Kleeblatt1977/status/693744048088162304"
        },
        {
            "retweets": 0,
            "favorites": 0,
            "text": "best kids delicious rezepte fr ihre iphone und ipad",
            "link": "https://twitter.com/irecipeapp/status/693726448440492034"
        },
        {
            "retweets": 0,
            "favorites": 0,
            "text": "ich starte ein raumschiff in meiner airport city ipad ipadgames gameinsight",
            "link": "https://twitter.com/WWong89/status/693723055365971972"
        },
        {
            "retweets": 0,
            "favorites": 0,
            "text": "original apple iphone ipad premium highspeed datenkabel ladekabel onlinecomoriginalappleiphoneipadpremiumhighspeeddatenkabelladekabel",
            "link": "https://twitter.com/BietenOnline/status/693718836281905152"
        },
        {
            "retweets": 0,
            "favorites": 0,
            "text": "pride of the ship ist eine wunderbare sammlung nur kein neid ipad ipadgames gameinsight",
            "link": "https://twitter.com/jessie_shorty81/status/693713509083922432"
        },
        {
            "retweets": 0,
            "favorites": 0,
            "text": "iphone ipad appstore preissenkung big guns weapon sound effects statt",
            "link": "https://twitter.com/AppTicker/status/693710410965450752"
        },
        {
            "retweets": 0,
            "favorites": 0,
            "text": "ich starte ein raumschiff in meiner airport city ipad ipadgames gameinsight",
            "link": "https://twitter.com/eberlmeister/status/693705416929247233"
        },
        {
            "retweets": 0,
            "favorites": 0,
            "text": "ich starte ein raumschiff in meiner airport city ipad ipadgames gameinsight",
            "link": "https://twitter.com/eberlmeister/status/693699208956788736"
        },
        {
            "retweets": 0,
            "favorites": 0,
            "text": "gutschein sonntagsdeal apple ipad mini smart cover apple ipad mini smart cover pu blau und grn nur am",
            "link": "https://twitter.com/Webgutscheine/status/693697162408890368"
        },
        {
            "retweets": 0,
            "favorites": 0,
            "text": "gutschein sonntagsdeal wacom intuos creative stylus wacom intuos creative stylus fr ipad ipad mini",
            "link": "https://twitter.com/Webgutscheine/status/693697161511333890"
        },
        {
            "retweets": 0,
            "favorites": 0,
            "text": "apple ipad mini gb wifi silber neu hndler paypal rechnung onlinecomappleipadminigbwifisilberneuhaendlerpaypalrechnung",
            "link": "https://twitter.com/BietenOnline/status/693697139541606401"
        },
        {
            "retweets": 0,
            "favorites": 0,
            "text": "hf beam antenna calculator iphone ipod app hamradio ipad",
            "link": "https://twitter.com/iPhoneAppDeal/status/693695205355053056"
        },
        {
            "retweets": 0,
            "favorites": 1,
            "text": "neu gebloggt deal sniffer heute mit ipad air keyboardcase flight control system powerbank gamingheadse",
            "link": "https://twitter.com/kaysxs/status/693694354481909760"
        },
        {
            "retweets": 0,
            "favorites": 0,
            "text": "apple ipad mini smart cover pu blau online kaufen im gravis shop autorisierter apple hndler gsgshadow undhuellenfuerappleipadschutzhuellenmitstandfunktionappleipadminismartcoverpublauhtmlforcesidbefdfcec",
            "link": "https://twitter.com/Berry2k8/status/693694088747618308"
        },
        {
            "retweets": 5,
            "favorites": 20,
            "text": "well guess im ready for bed goes up the stairs with sketchbook pencil glass of water ipad and headphones cantstopwontstop",
            "link": "https://twitter.com/AntonisaScott/status/693694064009580544"
        },
        {
            "retweets": 1,
            "favorites": 9,
            "text": "jeromy just sat up out of a dead sleep and started mutterscreaming looked at his ipad and went back to sleep i hope he isnt possessed",
            "link": "https://twitter.com/SydneyKay9/status/693693709896921088"
        },
        {
            "retweets": 1,
            "favorites": 0,
            "text": "google finally launches an adwordsapp for iphone and ipad",
            "link": "https://twitter.com/Vocatys/status/693691203896893442"
        },
        {
            "retweets": 0,
            "favorites": 0,
            "text": "langelier saturation index calculator lsi iphone water ipad app",
            "link": "https://twitter.com/iPhoneAppDeal/status/693689648850169856"
        },
        {
            "retweets": 0,
            "favorites": 0,
            "text": "ipad air caseesr yippee color series ipad air caseesr yippe pictwittercomsbwdwsdrbr",
            "link": "https://twitter.com/PS_Computer_/status/693689627526459392"
        },
        {
            "retweets": 0,
            "favorites": 0,
            "text": "apple ipad mini st generation gb wifi in white silver via ebay ipad pictwittercomwzegawmuv",
            "link": "https://twitter.com/giantshoppercom/status/693688278332104704"
        },
        {
            "retweets": 2,
            "favorites": 3,
            "text": "check out the decemberjanuary edition of law update now available to view online and download via our ipad app updatesectiondecemberjanuary",
            "link": "https://twitter.com/AlTamimiCompany/status/693685032716619776"
        },
        {
            "retweets": 6,
            "favorites": 2,
            "text": "paperless classroom app showbie now optimized for ipad pro and apple pencil",
            "link": "https://twitter.com/AppAdvice/status/693683910807547904"
        },
        {
            "retweets": 1,
            "favorites": 5,
            "text": "ipad pro pictwittercomwkpcrpbu",
            "link": "https://twitter.com/iup_date/status/693683020415414272"
        },
        {
            "retweets": 0,
            "favorites": 0,
            "text": "ebay iphone android lg g d gb gsm unlocked android tablet ipad salepictwittercomvrbkrzlo",
            "link": "https://twitter.com/AmazonBay4u/status/693680849137446912"
        },
        {
            "retweets": 12,
            "favorites": 129,
            "text": "babys first ipad pro doodle pictwittercomfmrjbona",
            "link": "https://twitter.com/space_ellien/status/693680628391346177"
        },
        {
            "retweets": 41,
            "favorites": 1,
            "text": "stickman trampoline pro extreme backflip frontflip action games sports ipad app",
            "link": "https://twitter.com/kathmego/status/693679422407245824"
        },
        {
            "retweets": 0,
            "favorites": 0,
            "text": "emperorleather crafterei ipad air hlletasche amarettini pictwittercomlycprqsklc",
            "link": "https://twitter.com/EmperorLeather/status/693679342598131712"
        },
        {
            "retweets": 0,
            "favorites": 0,
            "text": "apple ipad mini st generation gb wifi in white silver via ebay ipad pictwittercomrlnppdoqo",
            "link": "https://twitter.com/giantshoppercom/status/693676816263974912"
        },
        {
            "retweets": 6,
            "favorites": 12,
            "text": "expressreview apple ipad pro is a productive and portable pcreplacement says nandu pictwittercomuyvcgkzy",
            "link": "https://twitter.com/ExpressTechie/status/693675258201636864"
        },
        {
            "retweets": 1,
            "favorites": 10,
            "text": "i forgive you for stealing my ipad for an hour pictwittercomudqjwdvll",
            "link": "https://twitter.com/maddeemillerrrr/status/693675127263797250"
        },
        {
            "retweets": 0,
            "favorites": 0,
            "text": "iphone ipad appstore preissenkung phoenix photo editor statt",
            "link": "https://twitter.com/AppTicker/status/693674440098484225"
        },
        {
            "retweets": 0,
            "favorites": 0,
            "text": "fehler in ios mein iphone iniosmeiniphonesuchenlaesstsichohnepasswortdeaktivieren handy icloud ipad iphone ipod meiniphonesuchen phone smartphone",
            "link": "https://twitter.com/iFreeString/status/693674085214208000"
        },
        {
            "retweets": 0,
            "favorites": 0,
            "text": "apple ipad mini st generation gb wifi in white silver ipadministgenerationgbwifiinwhitesilver pictwittercomsnqwrtvsu",
            "link": "https://twitter.com/DigitalDealerCo/status/693672211614294016"
        },
        {
            "retweets": 0,
            "favorites": 6,
            "text": "instead of an actual stone with my name on it my tombstone will be an ipad with dave chappelle skits on loop until the end of time",
            "link": "https://twitter.com/justinhastings2/status/693672022014980096"
        },
        {
            "retweets": 15,
            "favorites": 3,
            "text": "dont swim with sharks beautiful endless runner free app now available on ios iphone ipad indiedev idrtg",
            "link": "https://twitter.com/TeachingOcean/status/693667674757296128"
        },
        {
            "retweets": 0,
            "favorites": 0,
            "text": "gutschein sonntagsdeal apple ipad mini smart cover apple ipad mini smart cover pu blau und grn nur am",
            "link": "https://twitter.com/24schnaeppchen/status/693667261257633792"
        },
        {
            "retweets": 0,
            "favorites": 0,
            "text": "gutschein sonntagsdeal wacom intuos creative stylus wacom intuos creative stylus fr ipad ipad mini",
            "link": "https://twitter.com/24schnaeppchen/status/693667260439744513"
        },
        {
            "retweets": 3,
            "favorites": 7,
            "text": "cmo eliminar libros kindle de tu iphone o ipad pictwittercomcrvlryly",
            "link": "https://twitter.com/applelizados/status/693667151798992896"
        },
        {
            "retweets": 1,
            "favorites": 1,
            "text": "win an ipad mini in the hunt to love our bodies love ourselves next monday am",
            "link": "https://twitter.com/snapdOkanagan/status/693664899998863360"
        },
        {
            "retweets": 0,
            "favorites": 0,
            "text": "apple ipad air st generation gb wifi in silver ipadair",
            "link": "https://twitter.com/iPadAirsales/status/693662582851424264"
        },
        {
            "retweets": 0,
            "favorites": 2,
            "text": "just saw a fightowensfight ko shirt at the gym but the guy was in the corner playing minecraft on his ipad disappointing",
            "link": "https://twitter.com/Glenntertain/status/693662344421900288"
        },
        {
            "retweets": 1,
            "favorites": 1,
            "text": "a high tech event each an ipad dubaisugarconferencepictwittercompsnwhyg",
            "link": "https://twitter.com/sugar_dubai/status/693661888199168000"
        },
        {
            "retweets": 5,
            "favorites": 3,
            "text": "retrogaming lovers will enjoy this new rpgadventure horror game for the ipad indiegamespictwittercommnjphaoqo",
            "link": "https://twitter.com/ArifGames/status/693660863841050624"
        },
        {
            "retweets": 0,
            "favorites": 8,
            "text": "i went to use my ipad for the first time in a while to find that it had been disabled for minutes which is almost years",
            "link": "https://twitter.com/macieadams_/status/693657143464083456"
        },
        {
            "retweets": 1,
            "favorites": 2,
            "text": "mom takes the ipad charger away and sarahg turns into the bitter queen of the south",
            "link": "https://twitter.com/queengisellexvi/status/693656906372554752"
        },
        {
            "retweets": 20,
            "favorites": 0,
            "text": "buildalot passport to europe hd full games simulation ipad",
            "link": "https://twitter.com/amyrightside/status/693655234002948097"
        },
        {
            "retweets": 20,
            "favorites": 0,
            "text": "asva the monkey hd games board ipad app gt free board ipad app ios",
            "link": "https://twitter.com/amyrightside/status/693655233419988992"
        },
        {
            "retweets": 4,
            "favorites": 9,
            "text": "nowwatching just like them horses by reba on vevo for ipad cant get enough of this pictwittercomwrxfngxd",
            "link": "https://twitter.com/Fancyreba1/status/693655148292390912"
        },
        {
            "retweets": 0,
            "favorites": 8,
            "text": "this is how we do the rolex overnight rockstar streaming the broadcast magnusracing live on the ipad pictwittercomajgvsjuxnc",
            "link": "https://twitter.com/IMSAchicks/status/693654516084953088"
        },
        {
            "retweets": 0,
            "favorites": 2,
            "text": "spotify on laptop ipad is better",
            "link": "https://twitter.com/beenessaa/status/693654456534069248"
        },
        {
            "retweets": 1,
            "favorites": 5,
            "text": "oreoheadd and we ate it off of my ipad",
            "link": "https://twitter.com/claftpunk/status/693654125637013504"
        },
        {
            "retweets": 0,
            "favorites": 3,
            "text": "did a quick thing on my ipad sometimes i wish i studied art dnd gnome teamteak ocpictwittercomjnivocdm",
            "link": "https://twitter.com/gnomedic/status/693653210964303872"
        },
        {
            "retweets": 1,
            "favorites": 18,
            "text": "i recommend to all ipad music makers the behringer istudio is the greatest investment midiaudio invideo out pictwittercombayzltot",
            "link": "https://twitter.com/kingbritt/status/693652977555476484"
        },
        {
            "retweets": 0,
            "favorites": 9,
            "text": "copped an ipad today oops notsorry",
            "link": "https://twitter.com/shoffner423/status/693652612411854848"
        },
        {
            "retweets": 3,
            "favorites": 65,
            "text": "sunday mrng homework primenumbers compositenumbers cantwaittoplay ipad minecraft skype",
            "link": "https://twitter.com/iamsonalibendre/status/693650328403734528"
        },
        {
            "retweets": 0,
            "favorites": 0,
            "text": "emperorleather crafterei ipad air hlletasche amarettini pictwittercomcroihar",
            "link": "https://twitter.com/EmperorLeather/status/693649203210383360"
        },
        {
            "retweets": 8,
            "favorites": 12,
            "text": "track conferences with stream reading perfect for ts with an iphone or ipad edtech gp pictwittercomwqzanq",
            "link": "https://twitter.com/ClassTechTips/status/693647536142290944"
        },
        {
            "retweets": 0,
            "favorites": 0,
            "text": "apple wireless charging ab fr iphone und ipad voondo",
            "link": "https://twitter.com/iPhoneTwitts/status/693644821026709504"
        },
        {
            "retweets": 1,
            "favorites": 3,
            "text": "my biggest down today was dropping my ipad down the steps tyler",
            "link": "https://twitter.com/AbbieRoda/status/693641867997663232"
        },
        {
            "retweets": 8,
            "favorites": 15,
            "text": "if he takes a selfie with an ipad run",
            "link": "https://twitter.com/halftruthss/status/693641308586536961"
        },
        {
            "retweets": 0,
            "favorites": 0,
            "text": "apple ipad mini st generation gb wifi in white silver ipadministgenerationgbwifiinwhitesilver pictwittercomurodpiltq",
            "link": "https://twitter.com/DigitalDealerCo/status/693640711057465344"
        },
        {
            "retweets": 0,
            "favorites": 0,
            "text": "korg im for ipad mobile music workstation software korg",
            "link": "https://twitter.com/sur_round/status/693640664282628096"
        },
        {
            "retweets": 0,
            "favorites": 2,
            "text": "my baby is so lovable he kissed his friend a boy on the shoulder while they were playing w the ipad the boy said ew wiped it off",
            "link": "https://twitter.com/biancanicole11/status/693640449777487872"
        },
        {
            "retweets": 0,
            "favorites": 0,
            "text": "neu zagg glass screen protector fr apple ipad air idglsf onlinecomneuzaggglassscreenprotectorfuerappleipadairidglsf",
            "link": "https://twitter.com/BietenOnline/status/693640136685330432"
        },
        {
            "retweets": 0,
            "favorites": 11,
            "text": "tonights seagul first ipad drawing with the apple pencil i like it a lotpictwittercomyjdbng",
            "link": "https://twitter.com/cheedoh/status/693637091503280128"
        },
        {
            "retweets": 6,
            "favorites": 3,
            "text": "state dept records show john kerry sent hillary a secret email from his ipad deptrecordsshowjohnkerrysenthillaryasecretemailfromhisipad",
            "link": "https://twitter.com/Nachumlist/status/693635490075906048"
        },
        {
            "retweets": 0,
            "favorites": 2,
            "text": "excited to present with classtechie in the ipad academy tcea",
            "link": "https://twitter.com/mathdebj/status/693635453195587589"
        },
        {
            "retweets": 0,
            "favorites": 3,
            "text": "i want an ipad to play on",
            "link": "https://twitter.com/ShihTzuP/status/693635423550083072"
        },
        {
            "retweets": 0,
            "favorites": 2,
            "text": "teddybcat marblesays itsmedeaner oh that reminds meteddy how to you delete apple apps i need more room on my ipad mini",
            "link": "https://twitter.com/MaryJeurissen/status/693634981940191232"
        },
        {
            "retweets": 0,
            "favorites": 6,
            "text": "fire alarm at fairmontcll kenzie grabbed her ipad but no shoes amber took everything she had i just have a rum evacaution lyncher",
            "link": "https://twitter.com/mmichaelsshow/status/693633763847200768"
        },
        {
            "retweets": 1,
            "favorites": 3,
            "text": "earlier i was sittinng on my bed with my school ipad old personal ipad and my new ipad miniwhat am i doing with my life and three ipads",
            "link": "https://twitter.com/demimschwartz/status/693633046818398208"
        },
        {
            "retweets": 62,
            "favorites": 201,
            "text": "parenting now shoving a fucking ipad in your kids face",
            "link": "https://twitter.com/LinaEdwardss/status/693632312861392896"
        },
        {
            "retweets": 1,
            "favorites": 2,
            "text": "i was on my ipad and ebackpack randomly pulls up out of nowherethe home button power button wont workis my ipad telling me to do my hw",
            "link": "https://twitter.com/emily_diesing/status/693632252761264128"
        },
        {
            "retweets": 0,
            "favorites": 0,
            "text": "apple ipad mini st generation gb wifi in white silver via ebay ipad rtpictwittercomiffbvfmhx",
            "link": "https://twitter.com/giantshoppercom/status/693631523585691648"
        },
        {
            "retweets": 0,
            "favorites": 2,
            "text": "my ipad has been plugged in all day and its only at",
            "link": "https://twitter.com/HeyItsKassidie/status/693629975799398403"
        },
        {
            "retweets": 2,
            "favorites": 1,
            "text": "is pastor getting a tattoo find out tomorrow at compel sunday win an ipad mini when you bring the most friends pictwittercombherhy",
            "link": "https://twitter.com/TrinityMiami/status/693625866031603712"
        },
        {
            "retweets": 0,
            "favorites": 2,
            "text": "now that ella has an ipad for communication she says eat pizza just as much as i always imagined she would",
            "link": "https://twitter.com/MotherTeresaJ/status/693625024188526592"
        },
        {
            "retweets": 0,
            "favorites": 1,
            "text": "stay on top of all nthe juiciest celebrity news with a free ipad air",
            "link": "https://twitter.com/T_Rex1962/status/693624901366710273"
        },
        {
            "retweets": 0,
            "favorites": 2,
            "text": "foggy winter day done with procreate and apple pencil on ipad pro pictwittercomprphlolwz",
            "link": "https://twitter.com/OttawaPete/status/693623160072118274"
        },
        {
            "retweets": 3,
            "favorites": 4,
            "text": "if youre not paying attention you may use an ipad as a plate",
            "link": "https://twitter.com/NolaChef504/status/693622778264616960"
        },
        {
            "retweets": 1,
            "favorites": 3,
            "text": "some of the best ipad apps for creating educational animations and video lessons educational technology and mo",
            "link": "https://twitter.com/VipulaSharma1/status/693622694424637441"
        },
        {
            "retweets": 53,
            "favorites": 171,
            "text": "love technology watching realbencarson live from iowa on ipad common sense answers",
            "link": "https://twitter.com/paspase/status/693618890652254208"
        },
        {
            "retweets": 0,
            "favorites": 1,
            "text": "anybody buy an ipad pro because they want to diagrammake mockups with the pencil",
            "link": "https://twitter.com/HeroicEric/status/693618066299572224"
        },
        {
            "retweets": 4,
            "favorites": 2,
            "text": "we know why kerry has been silent state dept records show john kerry sent hillary a secret email from his ipad",
            "link": "https://twitter.com/Jonijam/status/693616789549387776"
        },
        {
            "retweets": 0,
            "favorites": 6,
            "text": "mom she put cheese on my ipad things you didnt think your kids would do to each other",
            "link": "https://twitter.com/gregswan/status/693615183323910145"
        },
        {
            "retweets": 3,
            "favorites": 11,
            "text": "i asked jonathanblow how he can lecture about xb being unfocused while bringing his game to ipad pictwittercomidbjpix",
            "link": "https://twitter.com/CrazyJuan77/status/693613358709346305"
        },
        {
            "retweets": 4,
            "favorites": 6,
            "text": "beautiful chillpill godis ipadcase amazingplaces glacier formations pictwittercomnsyqkwjqzq",
            "link": "https://twitter.com/picsplaces/status/693613201896833025"
        },
        {
            "retweets": 0,
            "favorites": 22,
            "text": "the ipad password of the yearold im babysitting is",
            "link": "https://twitter.com/cfraney8/status/693612697452023811"
        },
        {
            "retweets": 0,
            "favorites": 8,
            "text": "my little cousin has like different minecraft games on her ipad im jealous",
            "link": "https://twitter.com/d_rob2_/status/693611670938087427"
        },
        {
            "retweets": 1,
            "favorites": 3,
            "text": "randomly discovered sweet multitasking on my ipad pictwittercomqvqvhbhocn",
            "link": "https://twitter.com/HalfCourtHoops/status/693611580030849024"
        },
        {
            "retweets": 3,
            "favorites": 25,
            "text": "my clan is amazing a clan mate broke his device and we raised enough to buy him an ipad in a week",
            "link": "https://twitter.com/AnthonyEclipse/status/693610001827524608"
        },
        {
            "retweets": 35,
            "favorites": 9,
            "text": "state dept records show john kerry sent hillary a secret email from his ipad deptrecordsshowjohnkerrysenthillaryasecretemailfromhisipad via chuckrossdc",
            "link": "https://twitter.com/ddraplin/status/693608555736223744"
        },
        {
            "retweets": 3,
            "favorites": 6,
            "text": "the first of our ipad monthly champions announced welcome to the family championsrzsz ipaded adedupictwittercomopljbjp",
            "link": "https://twitter.com/iPad_Monthly/status/693608050997858304"
        },
        {
            "retweets": 2,
            "favorites": 4,
            "text": "a ipad pro drawing in procreate bit by bit im getting used to it pictwittercomvtpdhygn",
            "link": "https://twitter.com/ferretface/status/693608016248193024"
        },
        {
            "retweets": 1,
            "favorites": 2,
            "text": "why the ipad is a bigger threat to our children than anyone realises whyipadfarbiggerthreatchildrenrealisestenyearsagopsychologistsuepalmerpredictedtoxiceffectssocialmediaseesworryingnewdangerhtml playmatters we prepare engaging play spaces",
            "link": "https://twitter.com/Roomtoplay/status/693605424340185089"
        },
        {
            "retweets": 1,
            "favorites": 8,
            "text": "little landscape study done on the ipad pro illustration digitalpainting digitalart s pictwittercomviprnkhwyb",
            "link": "https://twitter.com/fabric_8/status/693605383789776900"
        },
        {
            "retweets": 0,
            "favorites": 5,
            "text": "dont leave your twitter logged into my ipad megan love kennedy",
            "link": "https://twitter.com/Itzmeggo/status/693604435260370944"
        },
        {
            "retweets": 12,
            "favorites": 3,
            "text": "this is a great casual free game that everyone can enjoy indiedev gamedev ios ipad iphone idrtg",
            "link": "https://twitter.com/ElbowRoomApps/status/693604050932109312"
        },
        {
            "retweets": 0,
            "favorites": 8,
            "text": "i just saw a kid with a lanyard for his ipad the future is now",
            "link": "https://twitter.com/ayoitsdanyo/status/693601465726676992"
        },
        {
            "retweets": 63,
            "favorites": 31,
            "text": "state dept records show john kerry sent hillary clinton a secret email from his ipad pictwittercomlyoqnzudf",
            "link": "https://twitter.com/DailyCaller/status/693599596401049601"
        },
        {
            "retweets": 8,
            "favorites": 3,
            "text": "state dept records show john kerry sent hillary a secret email from his ipad",
            "link": "https://twitter.com/Jack6010/status/693598492736946176"
        },
        {
            "retweets": 3,
            "favorites": 9,
            "text": "grow your account and succeed on twitter try crowdfire now also on ipad",
            "link": "https://twitter.com/HunnyBegum/status/693597567133839360"
        },
        {
            "retweets": 0,
            "favorites": 0,
            "text": "choller pah ich hab die original ostsandmnnchenapp aufm ipad o",
            "link": "https://twitter.com/VolkerGoebbels/status/693595448796418048"
        },
        {
            "retweets": 3,
            "favorites": 15,
            "text": "i think fred figured out how to use ipad filters pictwittercomxfznc",
            "link": "https://twitter.com/kaaaattttY/status/693595099645755392"
        },
        {
            "retweets": 4,
            "favorites": 51,
            "text": "lighting courtesy of my ipad pictwittercomfvkdnvhsl",
            "link": "https://twitter.com/shiallrise/status/693594933572145152"
        },
        {
            "retweets": 3,
            "favorites": 17,
            "text": "was a fun experience playing on an ipad today but i think ill stick to my s haha",
            "link": "https://twitter.com/StatusVG/status/693591741086044160"
        },
        {
            "retweets": 2,
            "favorites": 37,
            "text": "xander likes to setup his ipad all over the room to record his little shows right now hes",
            "link": "https://twitter.com/Barnacules/status/693591645045026816"
        },
        {
            "retweets": 0,
            "favorites": 3,
            "text": "editing underwater image on ipad pro with pencil using the astropad app freakin amazing ipadpro applepencilpictwittercomcxkqdecvo",
            "link": "https://twitter.com/reynosophoto/status/693587497830330368"
        },
        {
            "retweets": 0,
            "favorites": 0,
            "text": "iphone ipad appstore preissenkung lan scan hd network device scanner statt",
            "link": "https://twitter.com/AppTicker/status/693587079775809538"
        },
        {
            "retweets": 0,
            "favorites": 0,
            "text": "iphone ipad appstore preissenkung crow statt",
            "link": "https://twitter.com/AppTicker/status/693586827123507200"
        },
        {
            "retweets": 0,
            "favorites": 0,
            "text": "apple ipad mini st generation gb wifi in black via ebay ipad rtpictwittercomoamvylr",
            "link": "https://twitter.com/giantshoppercom/status/693586300901941248"
        },
        {
            "retweets": 1,
            "favorites": 2,
            "text": "imovie video editing storytelling with your iphone or ipad star course minvideo tipspictwittercomouqghjs",
            "link": "https://twitter.com/SnowSugarVideo/status/693585509122048000"
        },
        {
            "retweets": 0,
            "favorites": 8,
            "text": "this kid is screaming at his mother telling her to die bc she took away his ipadwhat is this world coming to",
            "link": "https://twitter.com/Sydneehill23/status/693585367019175938"
        },
        {
            "retweets": 0,
            "favorites": 0,
            "text": "apple wireless charging ab fr iphone und ipad voondo",
            "link": "https://twitter.com/iPhoneTwitts/status/693584867569897472"
        },
        {
            "retweets": 0,
            "favorites": 2,
            "text": "mwotton its the pencil first true ipad stylus that actually works well enough to disrupt physical pens and pencils jotbamboo were crap",
            "link": "https://twitter.com/vgr/status/693584534906892289"
        },
        {
            "retweets": 0,
            "favorites": 0,
            "text": "nailsorbeauty are you using a mobile phone or and ipad sg",
            "link": "https://twitter.com/NatWest_Help/status/693584504007573504"
        },
        {
            "retweets": 0,
            "favorites": 0,
            "text": "cradle of rome hd games adventure ipad app pictwittercomirgrreoois",
            "link": "https://twitter.com/ginalimp/status/693584503650914304"
        },
        {
            "retweets": 0,
            "favorites": 0,
            "text": "akai ks cdg karaoke player with ipad cradle electronics drop",
            "link": "https://twitter.com/pricechirp/status/693584500782080002"
        },
        {
            "retweets": 1,
            "favorites": 1,
            "text": "some of the best ipad apps for creating educational animations and video lessons",
            "link": "https://twitter.com/SpiralEducation/status/693584497086889984"
        },
        {
            "retweets": 0,
            "favorites": 0,
            "text": "ipad mini giveaway freecomigmjh",
            "link": "https://twitter.com/AngelicaM63/status/693584480297160708"
        },
        {
            "retweets": 0,
            "favorites": 0,
            "text": "hurray ive completed the antiproblem hat quest in mystery manor game ipad ipadgames gameinsight",
            "link": "https://twitter.com/sunny_brown5/status/693584478837411840"
        }
    ]
}