{
    "2018-08-02": [
        {
            "retweets": 70,
            "favorites": 469,
            "text": "my boyfriend bought me a macbook for my birthday but i sold it so that i could go on a trip to new york with my male bestfriend bsu",
            "link": "https://twitter.com/HBCUfessions/status/1025139216114704384"
        },
        {
            "retweets": 0,
            "favorites": 0,
            "text": "i liked a youtube video macbook pro im handson euro fr einen laptop",
            "link": "https://twitter.com/One__Review/status/1025115413343023105"
        },
        {
            "retweets": 0,
            "favorites": 0,
            "text": "macbook und imac zurck bei airmail und fantastical undimaczurueckbeiairmailundfantastical pictwittercomxievaqv",
            "link": "https://twitter.com/smartphone_fan/status/1025102607164030976"
        },
        {
            "retweets": 0,
            "favorites": 0,
            "text": "anthony boyd graphics modern iphone x and macbook pro mockup vol iphonexandmacbookpromockupvol va anthonyjboydii",
            "link": "https://twitter.com/andbc/status/1025094211606069248"
        },
        {
            "retweets": 0,
            "favorites": 0,
            "text": "new silver apple macbook pro touch bar retina i ghz gb ram th gen",
            "link": "https://twitter.com/coozda/status/1025156447221501952"
        },
        {
            "retweets": 7,
            "favorites": 239,
            "text": "is there a way to create an adhoc network between an ipad and a macbook without a wifi bridge wired via charging cable",
            "link": "https://twitter.com/deadmau5/status/1025154592097497088"
        },
        {
            "retweets": 0,
            "favorites": 0,
            "text": "apple macbook pro zoll laptop notebook ghz gb ram macbookprozolllaptopnotebookghzgbram pictwittercomyeddgkqsr",
            "link": "https://twitter.com/gebl0ckt/status/1025150032427855872"
        },
        {
            "retweets": 12,
            "favorites": 121,
            "text": "apple hit a trillion because fools like me keep breaking that cheap screen damaging every mac book i have upgrading phones they purposely slow down and my need to have new everything",
            "link": "https://twitter.com/2LarryJohnson7/status/1025137865800536066"
        },
        {
            "retweets": 45,
            "favorites": 175,
            "text": "for a macbook charger jesus christ i cant believe they get away with this",
            "link": "https://twitter.com/ChuckieOnline/status/1025105135268245504"
        },
        {
            "retweets": 0,
            "favorites": 0,
            "text": "die letzten tage der bachelorarbeit sahen alle so aus catsofinstagram bachelorarbeit motivationshilfe kevin cat macbook pictwittercomvlgijnrhg",
            "link": "https://twitter.com/KayaSievers/status/1025086285474607104"
        },
        {
            "retweets": 14,
            "favorites": 94,
            "text": "i would argue that apple needs to be better than good enough the entire companys premise is that they deliver superior products and experiences the macbook air they will sell you today isnt even close to that standard",
            "link": "https://twitter.com/gruber/status/1025081654782709760"
        },
        {
            "retweets": 49,
            "favorites": 141,
            "text": "design share win design a business card using the lost alphabets from the bauhausdessau foundation and share it with us for a chance to win a macbook pro adobehiddentreasures contestpictwittercomrqlrwwlwa",
            "link": "https://twitter.com/Illustrator/status/1025078855420264450"
        },
        {
            "retweets": 10,
            "favorites": 48,
            "text": "now it is worth a trillion dollars apple can nearly afford to buy the top spec macbook pro trilliondollarcompany apple applestock",
            "link": "https://twitter.com/HAL9000_/status/1025077866457980929"
        },
        {
            "retweets": 5,
            "favorites": 59,
            "text": "if you sit an open macbook pro on top of a closed macbook pro the magnets in the bottom laptop make the other one think its lid closed",
            "link": "https://twitter.com/jckarter/status/1025066374845018113"
        },
        {
            "retweets": 46,
            "favorites": 223,
            "text": "want an excuse for asking your boss for a macbook pro with a touch bar you can now use it to debug your code in pycharm newinpycharm pictwittercomaipqawm",
            "link": "https://twitter.com/pycharm/status/1025060418920828928"
        },
        {
            "retweets": 8,
            "favorites": 42,
            "text": "seokjin had a macbook with the windows os running and a picture of himself as his wallpaper truly iconic",
            "link": "https://twitter.com/natsooee/status/1025047221132189696"
        },
        {
            "retweets": 0,
            "favorites": 1,
            "text": "satechi typ c usb in combohub mit usbc passthroughcharging aus aluminium fr das macbook zoll space grau",
            "link": "https://twitter.com/Tobi_Marimba/status/1025041636575928325"
        },
        {
            "retweets": 832,
            "favorites": 5200,
            "text": "apple being with trillion is nuts with trillion you could buy billion iphone x million macbook pros million imac pros million model s million k homes",
            "link": "https://twitter.com/tldtoday/status/1025037969910951936"
        },
        {
            "retweets": 4,
            "favorites": 105,
            "text": "i love my little macbook but it just isnt able to handle intense excel spreadsheets",
            "link": "https://twitter.com/deray/status/1025023140005666818"
        },
        {
            "retweets": 0,
            "favorites": 1,
            "text": "ich mag das youtubevideo macbook pro im handson euro fr einen laptop",
            "link": "https://twitter.com/iTechniklife/status/1025022297084776448"
        },
        {
            "retweets": 11,
            "favorites": 46,
            "text": "apple considers alternative macbook keyboards with touch interfaces improved dust protection considersalternativemacbookkeyboardswithtouchinterfacesimproveddustprotection pictwittercomlwrdorjos",
            "link": "https://twitter.com/appleinsider/status/1025017384338436096"
        },
        {
            "retweets": 0,
            "favorites": 0,
            "text": "topmonitore fr macbook und co",
            "link": "https://twitter.com/macwelt/status/1025001563327291392"
        },
        {
            "retweets": 0,
            "favorites": 0,
            "text": "derweil drben auf macbook pro test fazit nach wochen zoll quadcore protestfazitnachwochenzollquadcore",
            "link": "https://twitter.com/maczeug/status/1024966567052890112"
        },
        {
            "retweets": 0,
            "favorites": 0,
            "text": "mini displayport to hdmi vga dvi adapter foinnex thunderbolt mini dp converter for apple macmacbook prosurface pro pro surface bookmacbook airimac monitorprojectortv foinnex",
            "link": "https://twitter.com/gorillaposition/status/1024951272263147520"
        },
        {
            "retweets": 0,
            "favorites": 6,
            "text": "my ros wine matches my ros gold macbook",
            "link": "https://twitter.com/rystant/status/1024901307562254336"
        },
        {
            "retweets": 0,
            "favorites": 0,
            "text": "apple macbook air cm zoll notebook intel core i u ghz intel hd graphics gb ram gb flashspeicher modell juni macbookaircmzollnotebookintelcoreiughzintelhdgraphicsgbramgbflashspeichermodelljuni pictwittercomiyvveihior",
            "link": "https://twitter.com/hsc_24/status/1024897612422504449"
        },
        {
            "retweets": 0,
            "favorites": 0,
            "text": "pc maus topelek laptop maus schnurlos g dpi wireless drahtlose mouse optical business mouse usb funkmaus optische muse tasten fr imac macbook microsoft pro office home deep blue maustopeleklaptopmausschnurlosgdpiwirelessdrahtlosemouseopticalbusinessmouseusbfunkmausoptischemaeusetastenfuerimacmacbookmicrosoftproofficehomedeepblue pictwittercomerfqhvh",
            "link": "https://twitter.com/hsc_24/status/1024893586117144576"
        },
        {
            "retweets": 14,
            "favorites": 5,
            "text": "amazoniphone xipad air promacbook pro pictwittercomdnkprtibhq",
            "link": "https://twitter.com/yasutoshi_r/status/1024871490825506816"
        },
        {
            "retweets": 2,
            "favorites": 53,
            "text": "me sitting at a coffee shop on my macbook downloading new music",
            "link": "https://twitter.com/CassTolliver/status/1024869681331662848"
        },
        {
            "retweets": 47,
            "favorites": 149,
            "text": "if i compare living in a voluntary market system where i purchase all kinds of useless luxury shit to the broad concept of society itself i wont feel bad for buying that macbook socialists pictwittercomkycqmfexa",
            "link": "https://twitter.com/CatlinNyaa/status/1024857939113324545"
        },
        {
            "retweets": 1,
            "favorites": 20,
            "text": "side note my dad got a macbook for his birthday yesterday so we are officially an apple family excluding my mom who still doesnt know what copy paste is literally last year we almost lost our home and now we all have macbooks the definition of middle class",
            "link": "https://twitter.com/fern_marr/status/1024849176163745792"
        },
        {
            "retweets": 38,
            "favorites": 537,
            "text": "the current macbook air should be sold for and not a penny more its a disgrace in especially at its absurd price point of",
            "link": "https://twitter.com/SnazzyQ/status/1024843368428261376"
        },
        {
            "retweets": 4,
            "favorites": 18,
            "text": "heres a shitty raspy macbook cover of midnight by sos pictwittercomaizobmkg",
            "link": "https://twitter.com/owndamngame/status/1024837071850987520"
        },
        {
            "retweets": 0,
            "favorites": 1,
            "text": "macbook pro silver late ghz i gb gb applecare ebay prosilverlateghzigbgbapplecareiidtrkparmsacafeatured pictwittercomhsohljzby",
            "link": "https://twitter.com/SandyAlz/status/1024829953265807361"
        },
        {
            "retweets": 5,
            "favorites": 71,
            "text": "think im gonna return my new macbook after about months of use many of the keys no longer provide any tactile feedback at all makes it impossible to type stuff quickly because im not sure of the keys has been pressed",
            "link": "https://twitter.com/mjackson/status/1024829377299787776"
        },
        {
            "retweets": 0,
            "favorites": 0,
            "text": "timetec hynix ic apple gb kit xgb ddr pc mhz memory upgrade for imac inch inch inch inch macbook pro inch inch inch mac mini gb kit xgb pictwittercomaeosxnh",
            "link": "https://twitter.com/InstantTimeDeal/status/1024829162207543296"
        },
        {
            "retweets": 6,
            "favorites": 24,
            "text": "hi applesupport im here to report an issue with my macbook pro",
            "link": "https://twitter.com/Steven_Cusumano/status/1024826291147735041"
        },
        {
            "retweets": 10,
            "favorites": 248,
            "text": "this is the gold macbook look at that color variance between the body and trackpad ewwwww pictwittercomrjrvnshz",
            "link": "https://twitter.com/Jon4Lakers/status/1024814833479249921"
        },
        {
            "retweets": 4,
            "favorites": 15,
            "text": "he definitely still uses that at home will only consider upgrading to a macbook air of exceptional quality if an offer presents itself afc",
            "link": "https://twitter.com/JamesDoddFOX/status/1024809371497197568"
        },
        {
            "retweets": 0,
            "favorites": 1,
            "text": "i get more indepth here but overall the trackpad doesnt feel quite as precise as the macbook out of the box but with lots of tweaking its getting close i am already used to it",
            "link": "https://twitter.com/themikepan/status/1024809040130408450"
        },
        {
            "retweets": 0,
            "favorites": 0,
            "text": "macbook pro non touch bar ghz i gb ram gb ssd brand new no box new original charger included apple care plus warranty until march firm price retail",
            "link": "https://twitter.com/MLG_Dope/status/1024808608666542080"
        },
        {
            "retweets": 0,
            "favorites": 1,
            "text": "i noticed there were school districts in indiana and kentucky that were using the elearning day concept this past winter with schools giving students chromebooks macbook minis and ipads it was just a matter of time until more district implemented the policy",
            "link": "https://twitter.com/mlgriffinWX1/status/1024808188279963648"
        },
        {
            "retweets": 0,
            "favorites": 2,
            "text": "lol its light years different now documentation is excellent hardware support solid i almost have it working on a macbook pro its there blame bcmxx",
            "link": "https://twitter.com/dyn___/status/1024807888303190017"
        },
        {
            "retweets": 0,
            "favorites": 1,
            "text": "uniformity is great no light leaks in corners even in a pitch black room since its an ips panel viewing angle is perfect the glass screen is a lot more reflective than a macbook though linux review coming soon pictwittercomajousnke",
            "link": "https://twitter.com/themikepan/status/1024807656987353088"
        },
        {
            "retweets": 0,
            "favorites": 1,
            "text": "my macbook does the opposite it just turns off on itself",
            "link": "https://twitter.com/lovelylauv/status/1024807656651931654"
        },
        {
            "retweets": 0,
            "favorites": 3,
            "text": "byodpodcast macbook air mirror present for natisho he sure loves that macbook air pictwittercomdyumanvaj",
            "link": "https://twitter.com/RyanWalkerDJ/status/1024807515861774337"
        },
        {
            "retweets": 0,
            "favorites": 1,
            "text": "unfortunately a few weeks ago some douchebags stole my macbook pro so i got to buy another one and guess what the same fucking problem with the keyboard wtf apple",
            "link": "https://twitter.com/shibatmann/status/1024807399247564802"
        },
        {
            "retweets": 0,
            "favorites": 0,
            "text": "for sure and its not just the consumer im still happily using a for prolevel work but i think youre missing the point which is that the air is lousy tech for today and i really cant see why they cant sell the macbook for that price",
            "link": "https://twitter.com/josh_m/status/1024807213875978240"
        },
        {
            "retweets": 0,
            "favorites": 0,
            "text": "tomorrowwere going live on facebook to announce the lucky winner of our ready set refer challenge tune in at est to find out whos taking home cash or a macbook air readysetrefer referral challenge happygrasshopper prize",
            "link": "https://twitter.com/HappyGhopper/status/1024807197564395521"
        },
        {
            "retweets": 0,
            "favorites": 0,
            "text": "heavy duty protective case for macbook pro inch apply now and review here at tomoson campaigns reviewspictwittercomfhslonx",
            "link": "https://twitter.com/TomosonReviews/status/1024807025224634369"
        },
        {
            "retweets": 1,
            "favorites": 0,
            "text": "my answer is it depends i love my macbook i loved my t love my xps but those new thinkpads make me want to leave my xps particularly im looking forward to the upcoming ryzen pro thinkpads",
            "link": "https://twitter.com/taekicks/status/1024806994090188800"
        },
        {
            "retweets": 0,
            "favorites": 0,
            "text": "apple wins dismissal of lawsuit over macbook logic boards applemacbooklawsuitapplewinsdismissaloflawsuitovermacbooklogicboardsiduskbnkiafeedtyperssfeednamevcmedia",
            "link": "https://twitter.com/social_rosie/status/1024806993385668608"
        },
        {
            "retweets": 0,
            "favorites": 0,
            "text": "apple macbook air mclla inch laptop certified refurbished mcllinchcertifiedrefurbisheddpbzdepscsubscriptionidakiaipssbccklxdkaqtagemmsgadblolinkcodexmcampcreativecreativeasinbzde pictwittercomrcktjmhihd",
            "link": "https://twitter.com/EKAffiliates/status/1024806992995606529"
        }
    ]
}